{
  "header" : {
    "uri" : "https://api.ordnancesurvey.co.uk/places/v1/addresses/postcode?postcode=bs70se",
    "query" : "postcode=bs70se",
    "offset" : 0,
    "totalresults" : 27,
    "format" : "JSON",
    "dataset" : "DPA",
    "lr" : "EN,CY",
    "maxresults" : 100,
    "epoch" : "69",
    "output_srs" : "EPSG:27700"
  },
  "results" : [ {
    "DPA" : {
      "UPRN" : "500554",
      "UDPRN" : "2764575",
      "ADDRESS" : "1, BRONCKSEA ROAD, BRISTOL, BS7 0SE",
      "BUILDING_NUMBER" : "1",
      "THOROUGHFARE_NAME" : "BRONCKSEA ROAD",
      "POST_TOWN" : "BRISTOL",
      "POSTCODE" : "BS7 0SE",
      "RPC" : "1",
      "X_COORDINATE" : 359865.0,
      "Y_COORDINATE" : 178356.0,
      "STATUS" : "APPROVED",
      "LOGICAL_STATUS_CODE" : "1",
      "CLASSIFICATION_CODE" : "RI01",
      "CLASSIFICATION_CODE_DESCRIPTION" : "Care / Nursing Home",
      "LOCAL_CUSTODIAN_CODE" : 119,
      "LOCAL_CUSTODIAN_CODE_DESCRIPTION" : "SOUTH GLOUCESTERSHIRE",
      "POSTAL_ADDRESS_CODE" : "D",
      "POSTAL_ADDRESS_CODE_DESCRIPTION" : "A record which is linked to PAF",
      "BLPU_STATE_CODE" : "2",
      "BLPU_STATE_CODE_DESCRIPTION" : "In use",
      "TOPOGRAPHY_LAYER_TOID" : "osgb1000015017295",
      "LAST_UPDATE_DATE" : "24/04/2019",
      "ENTRY_DATE" : "01/04/1999",
      "BLPU_STATE_DATE" : "25/06/2010",
      "LANGUAGE" : "EN",
      "MATCH" : 1.0,
      "MATCH_DESCRIPTION" : "EXACT"
    }
  }, {
    "DPA" : {
      "UPRN" : "500565",
      "UDPRN" : "2764586",
      "ADDRESS" : "2, BRONCKSEA ROAD, BRISTOL, BS7 0SE",
      "BUILDING_NUMBER" : "2",
      "THOROUGHFARE_NAME" : "BRONCKSEA ROAD",
      "POST_TOWN" : "BRISTOL",
      "POSTCODE" : "BS7 0SE",
      "RPC" : "1",
      "X_COORDINATE" : 359865.0,
      "Y_COORDINATE" : 178398.0,
      "STATUS" : "APPROVED",
      "LOGICAL_STATUS_CODE" : "1",
      "CLASSIFICATION_CODE" : "RD02",
      "CLASSIFICATION_CODE_DESCRIPTION" : "Detached",
      "LOCAL_CUSTODIAN_CODE" : 119,
      "LOCAL_CUSTODIAN_CODE_DESCRIPTION" : "SOUTH GLOUCESTERSHIRE",
      "POSTAL_ADDRESS_CODE" : "D",
      "POSTAL_ADDRESS_CODE_DESCRIPTION" : "A record which is linked to PAF",
      "BLPU_STATE_CODE" : "2",
      "BLPU_STATE_CODE_DESCRIPTION" : "In use",
      "TOPOGRAPHY_LAYER_TOID" : "osgb1000015017343",
      "LAST_UPDATE_DATE" : "24/04/2019",
      "ENTRY_DATE" : "01/04/1999",
      "BLPU_STATE_DATE" : "01/12/2011",
      "LANGUAGE" : "EN",
      "MATCH" : 1.0,
      "MATCH_DESCRIPTION" : "EXACT"
    }
  }, {
    "DPA" : {
      "UPRN" : "500570",
      "UDPRN" : "2764591",
      "ADDRESS" : "3, BRONCKSEA ROAD, BRISTOL, BS7 0SE",
      "BUILDING_NUMBER" : "3",
      "THOROUGHFARE_NAME" : "BRONCKSEA ROAD",
      "POST_TOWN" : "BRISTOL",
      "POSTCODE" : "BS7 0SE",
      "RPC" : "1",
      "X_COORDINATE" : 359851.0,
      "Y_COORDINATE" : 178360.0,
      "STATUS" : "APPROVED",
      "LOGICAL_STATUS_CODE" : "1",
      "CLASSIFICATION_CODE" : "RD03",
      "CLASSIFICATION_CODE_DESCRIPTION" : "Semi-Detached",
      "LOCAL_CUSTODIAN_CODE" : 119,
      "LOCAL_CUSTODIAN_CODE_DESCRIPTION" : "SOUTH GLOUCESTERSHIRE",
      "POSTAL_ADDRESS_CODE" : "D",
      "POSTAL_ADDRESS_CODE_DESCRIPTION" : "A record which is linked to PAF",
      "BLPU_STATE_CODE" : "2",
      "BLPU_STATE_CODE_DESCRIPTION" : "In use",
      "TOPOGRAPHY_LAYER_TOID" : "osgb1000015017297",
      "LAST_UPDATE_DATE" : "24/04/2019",
      "ENTRY_DATE" : "01/04/1999",
      "BLPU_STATE_DATE" : "01/12/2011",
      "LANGUAGE" : "EN",
      "MATCH" : 1.0,
      "MATCH_DESCRIPTION" : "EXACT"
    }
  }, {
    "DPA" : {
      "UPRN" : "500571",
      "UDPRN" : "2764593",
      "ADDRESS" : "4, BRONCKSEA ROAD, BRISTOL, BS7 0SE",
      "BUILDING_NUMBER" : "4",
      "THOROUGHFARE_NAME" : "BRONCKSEA ROAD",
      "POST_TOWN" : "BRISTOL",
      "POSTCODE" : "BS7 0SE",
      "RPC" : "2",
      "X_COORDINATE" : 359852.0,
      "Y_COORDINATE" : 178403.0,
      "STATUS" : "APPROVED",
      "LOGICAL_STATUS_CODE" : "1",
      "CLASSIFICATION_CODE" : "RD04",
      "CLASSIFICATION_CODE_DESCRIPTION" : "Terraced",
      "LOCAL_CUSTODIAN_CODE" : 119,
      "LOCAL_CUSTODIAN_CODE_DESCRIPTION" : "SOUTH GLOUCESTERSHIRE",
      "POSTAL_ADDRESS_CODE" : "D",
      "POSTAL_ADDRESS_CODE_DESCRIPTION" : "A record which is linked to PAF",
      "BLPU_STATE_CODE" : "2",
      "BLPU_STATE_CODE_DESCRIPTION" : "In use",
      "TOPOGRAPHY_LAYER_TOID" : "osgb1000015017346",
      "LAST_UPDATE_DATE" : "24/04/2019",
      "ENTRY_DATE" : "01/04/1999",
      "BLPU_STATE_DATE" : "01/12/2011",
      "LANGUAGE" : "EN",
      "MATCH" : 1.0,
      "MATCH_DESCRIPTION" : "EXACT"
    }
  }, {
    "DPA" : {
      "UPRN" : "500572",
      "UDPRN" : "2764594",
      "ADDRESS" : "5, BRONCKSEA ROAD, BRISTOL, BS7 0SE",
      "BUILDING_NUMBER" : "5",
      "THOROUGHFARE_NAME" : "BRONCKSEA ROAD",
      "POST_TOWN" : "BRISTOL",
      "POSTCODE" : "BS7 0SE",
      "RPC" : "2",
      "X_COORDINATE" : 359834.0,
      "Y_COORDINATE" : 178368.0,
      "STATUS" : "APPROVED",
      "LOGICAL_STATUS_CODE" : "1",
      "CLASSIFICATION_CODE" : "RD03",
      "CLASSIFICATION_CODE_DESCRIPTION" : "Semi-Detached",
      "LOCAL_CUSTODIAN_CODE" : 119,
      "LOCAL_CUSTODIAN_CODE_DESCRIPTION" : "SOUTH GLOUCESTERSHIRE",
      "POSTAL_ADDRESS_CODE" : "D",
      "POSTAL_ADDRESS_CODE_DESCRIPTION" : "A record which is linked to PAF",
      "BLPU_STATE_CODE" : "2",
      "BLPU_STATE_CODE_DESCRIPTION" : "In use",
      "TOPOGRAPHY_LAYER_TOID" : "osgb1000015017303",
      "LAST_UPDATE_DATE" : "24/04/2019",
      "ENTRY_DATE" : "01/04/1999",
      "BLPU_STATE_DATE" : "01/12/2011",
      "LANGUAGE" : "EN",
      "MATCH" : 1.0,
      "MATCH_DESCRIPTION" : "EXACT"
    }
  }, {
    "DPA" : {
      "UPRN" : "500573",
      "UDPRN" : "2764595",
      "ADDRESS" : "6, BRONCKSEA ROAD, BRISTOL, BS7 0SE",
      "BUILDING_NUMBER" : "6",
      "THOROUGHFARE_NAME" : "BRONCKSEA ROAD",
      "POST_TOWN" : "BRISTOL",
      "POSTCODE" : "BS7 0SE",
      "RPC" : "2",
      "X_COORDINATE" : 359846.0,
      "Y_COORDINATE" : 178404.0,
      "STATUS" : "APPROVED",
      "LOGICAL_STATUS_CODE" : "1",
      "CLASSIFICATION_CODE" : "RD04",
      "CLASSIFICATION_CODE_DESCRIPTION" : "Terraced",
      "LOCAL_CUSTODIAN_CODE" : 119,
      "LOCAL_CUSTODIAN_CODE_DESCRIPTION" : "SOUTH GLOUCESTERSHIRE",
      "POSTAL_ADDRESS_CODE" : "D",
      "POSTAL_ADDRESS_CODE_DESCRIPTION" : "A record which is linked to PAF",
      "BLPU_STATE_CODE" : "2",
      "BLPU_STATE_CODE_DESCRIPTION" : "In use",
      "TOPOGRAPHY_LAYER_TOID" : "osgb1000015017347",
      "LAST_UPDATE_DATE" : "24/04/2019",
      "ENTRY_DATE" : "01/04/1999",
      "BLPU_STATE_DATE" : "01/12/2011",
      "LANGUAGE" : "EN",
      "MATCH" : 1.0,
      "MATCH_DESCRIPTION" : "EXACT"
    }
  }, {
    "DPA" : {
      "UPRN" : "500574",
      "UDPRN" : "2764596",
      "ADDRESS" : "7, BRONCKSEA ROAD, BRISTOL, BS7 0SE",
      "BUILDING_NUMBER" : "7",
      "THOROUGHFARE_NAME" : "BRONCKSEA ROAD",
      "POST_TOWN" : "BRISTOL",
      "POSTCODE" : "BS7 0SE",
      "RPC" : "1",
      "X_COORDINATE" : 359828.0,
      "Y_COORDINATE" : 178370.0,
      "STATUS" : "APPROVED",
      "LOGICAL_STATUS_CODE" : "1",
      "CLASSIFICATION_CODE" : "RD03",
      "CLASSIFICATION_CODE_DESCRIPTION" : "Semi-Detached",
      "LOCAL_CUSTODIAN_CODE" : 119,
      "LOCAL_CUSTODIAN_CODE_DESCRIPTION" : "SOUTH GLOUCESTERSHIRE",
      "POSTAL_ADDRESS_CODE" : "D",
      "POSTAL_ADDRESS_CODE_DESCRIPTION" : "A record which is linked to PAF",
      "BLPU_STATE_CODE" : "2",
      "BLPU_STATE_CODE_DESCRIPTION" : "In use",
      "TOPOGRAPHY_LAYER_TOID" : "osgb1000015017304",
      "LAST_UPDATE_DATE" : "24/04/2019",
      "ENTRY_DATE" : "01/04/1999",
      "BLPU_STATE_DATE" : "01/12/2011",
      "LANGUAGE" : "EN",
      "MATCH" : 1.0,
      "MATCH_DESCRIPTION" : "EXACT"
    }
  }, {
    "DPA" : {
      "UPRN" : "607961",
      "UDPRN" : "2764597",
      "ADDRESS" : "8, BRONCKSEA ROAD, BRISTOL, BS7 0SE",
      "BUILDING_NUMBER" : "8",
      "THOROUGHFARE_NAME" : "BRONCKSEA ROAD",
      "POST_TOWN" : "BRISTOL",
      "POSTCODE" : "BS7 0SE",
      "RPC" : "2",
      "X_COORDINATE" : 359839.22,
      "Y_COORDINATE" : 178404.68,
      "STATUS" : "APPROVED",
      "LOGICAL_STATUS_CODE" : "1",
      "CLASSIFICATION_CODE" : "RD04",
      "CLASSIFICATION_CODE_DESCRIPTION" : "Terraced",
      "LOCAL_CUSTODIAN_CODE" : 119,
      "LOCAL_CUSTODIAN_CODE_DESCRIPTION" : "SOUTH GLOUCESTERSHIRE",
      "POSTAL_ADDRESS_CODE" : "D",
      "POSTAL_ADDRESS_CODE_DESCRIPTION" : "A record which is linked to PAF",
      "BLPU_STATE_CODE" : "2",
      "BLPU_STATE_CODE_DESCRIPTION" : "In use",
      "TOPOGRAPHY_LAYER_TOID" : "osgb1000015017348",
      "LAST_UPDATE_DATE" : "24/04/2019",
      "ENTRY_DATE" : "12/05/2000",
      "BLPU_STATE_DATE" : "01/12/2011",
      "LANGUAGE" : "EN",
      "MATCH" : 1.0,
      "MATCH_DESCRIPTION" : "EXACT"
    }
  }, {
    "DPA" : {
      "UPRN" : "500576",
      "UDPRN" : "2764598",
      "ADDRESS" : "9, BRONCKSEA ROAD, BRISTOL, BS7 0SE",
      "BUILDING_NUMBER" : "9",
      "THOROUGHFARE_NAME" : "BRONCKSEA ROAD",
      "POST_TOWN" : "BRISTOL",
      "POSTCODE" : "BS7 0SE",
      "RPC" : "1",
      "X_COORDINATE" : 359819.0,
      "Y_COORDINATE" : 178374.0,
      "STATUS" : "APPROVED",
      "LOGICAL_STATUS_CODE" : "1",
      "CLASSIFICATION_CODE" : "RD04",
      "CLASSIFICATION_CODE_DESCRIPTION" : "Terraced",
      "LOCAL_CUSTODIAN_CODE" : 119,
      "LOCAL_CUSTODIAN_CODE_DESCRIPTION" : "SOUTH GLOUCESTERSHIRE",
      "POSTAL_ADDRESS_CODE" : "D",
      "POSTAL_ADDRESS_CODE_DESCRIPTION" : "A record which is linked to PAF",
      "BLPU_STATE_CODE" : "2",
      "BLPU_STATE_CODE_DESCRIPTION" : "In use",
      "TOPOGRAPHY_LAYER_TOID" : "osgb1000015017307",
      "LAST_UPDATE_DATE" : "24/04/2019",
      "ENTRY_DATE" : "01/04/1999",
      "BLPU_STATE_DATE" : "01/12/2011",
      "LANGUAGE" : "EN",
      "MATCH" : 1.0,
      "MATCH_DESCRIPTION" : "EXACT"
    }
  }, {
    "DPA" : {
      "UPRN" : "500555",
      "UDPRN" : "2764576",
      "ADDRESS" : "10, BRONCKSEA ROAD, BRISTOL, BS7 0SE",
      "BUILDING_NUMBER" : "10",
      "THOROUGHFARE_NAME" : "BRONCKSEA ROAD",
      "POST_TOWN" : "BRISTOL",
      "POSTCODE" : "BS7 0SE",
      "RPC" : "1",
      "X_COORDINATE" : 359824.0,
      "Y_COORDINATE" : 178410.0,
      "STATUS" : "APPROVED",
      "LOGICAL_STATUS_CODE" : "1",
      "CLASSIFICATION_CODE" : "RD02",
      "CLASSIFICATION_CODE_DESCRIPTION" : "Detached",
      "LOCAL_CUSTODIAN_CODE" : 119,
      "LOCAL_CUSTODIAN_CODE_DESCRIPTION" : "SOUTH GLOUCESTERSHIRE",
      "POSTAL_ADDRESS_CODE" : "D",
      "POSTAL_ADDRESS_CODE_DESCRIPTION" : "A record which is linked to PAF",
      "BLPU_STATE_CODE" : "2",
      "BLPU_STATE_CODE_DESCRIPTION" : "In use",
      "TOPOGRAPHY_LAYER_TOID" : "osgb1000015017352",
      "LAST_UPDATE_DATE" : "24/04/2019",
      "ENTRY_DATE" : "01/04/1999",
      "BLPU_STATE_DATE" : "01/12/2011",
      "LANGUAGE" : "EN",
      "MATCH" : 1.0,
      "MATCH_DESCRIPTION" : "EXACT"
    }
  }, {
    "DPA" : {
      "UPRN" : "500556",
      "UDPRN" : "2764577",
      "ADDRESS" : "11, BRONCKSEA ROAD, BRISTOL, BS7 0SE",
      "BUILDING_NUMBER" : "11",
      "THOROUGHFARE_NAME" : "BRONCKSEA ROAD",
      "POST_TOWN" : "BRISTOL",
      "POSTCODE" : "BS7 0SE",
      "RPC" : "1",
      "X_COORDINATE" : 359812.0,
      "Y_COORDINATE" : 178374.0,
      "STATUS" : "APPROVED",
      "LOGICAL_STATUS_CODE" : "1",
      "CLASSIFICATION_CODE" : "RD04",
      "CLASSIFICATION_CODE_DESCRIPTION" : "Terraced",
      "LOCAL_CUSTODIAN_CODE" : 119,
      "LOCAL_CUSTODIAN_CODE_DESCRIPTION" : "SOUTH GLOUCESTERSHIRE",
      "POSTAL_ADDRESS_CODE" : "D",
      "POSTAL_ADDRESS_CODE_DESCRIPTION" : "A record which is linked to PAF",
      "BLPU_STATE_CODE" : "2",
      "BLPU_STATE_CODE_DESCRIPTION" : "In use",
      "TOPOGRAPHY_LAYER_TOID" : "osgb1000015017308",
      "LAST_UPDATE_DATE" : "24/04/2019",
      "ENTRY_DATE" : "01/04/1999",
      "BLPU_STATE_DATE" : "01/12/2011",
      "LANGUAGE" : "EN",
      "MATCH" : 1.0,
      "MATCH_DESCRIPTION" : "EXACT"
    }
  }, {
    "DPA" : {
      "UPRN" : "500557",
      "UDPRN" : "2764578",
      "ADDRESS" : "12, BRONCKSEA ROAD, BRISTOL, BS7 0SE",
      "BUILDING_NUMBER" : "12",
      "THOROUGHFARE_NAME" : "BRONCKSEA ROAD",
      "POST_TOWN" : "BRISTOL",
      "POSTCODE" : "BS7 0SE",
      "RPC" : "1",
      "X_COORDINATE" : 359815.0,
      "Y_COORDINATE" : 178414.0,
      "STATUS" : "APPROVED",
      "LOGICAL_STATUS_CODE" : "1",
      "CLASSIFICATION_CODE" : "RD02",
      "CLASSIFICATION_CODE_DESCRIPTION" : "Detached",
      "LOCAL_CUSTODIAN_CODE" : 119,
      "LOCAL_CUSTODIAN_CODE_DESCRIPTION" : "SOUTH GLOUCESTERSHIRE",
      "POSTAL_ADDRESS_CODE" : "D",
      "POSTAL_ADDRESS_CODE_DESCRIPTION" : "A record which is linked to PAF",
      "BLPU_STATE_CODE" : "2",
      "BLPU_STATE_CODE_DESCRIPTION" : "In use",
      "TOPOGRAPHY_LAYER_TOID" : "osgb1000015017353",
      "LAST_UPDATE_DATE" : "24/04/2019",
      "ENTRY_DATE" : "01/04/1999",
      "BLPU_STATE_DATE" : "01/12/2011",
      "LANGUAGE" : "EN",
      "MATCH" : 1.0,
      "MATCH_DESCRIPTION" : "EXACT"
    }
  }, {
    "DPA" : {
      "UPRN" : "500558",
      "UDPRN" : "2764579",
      "ADDRESS" : "13, BRONCKSEA ROAD, BRISTOL, BS7 0SE",
      "BUILDING_NUMBER" : "13",
      "THOROUGHFARE_NAME" : "BRONCKSEA ROAD",
      "POST_TOWN" : "BRISTOL",
      "POSTCODE" : "BS7 0SE",
      "RPC" : "2",
      "X_COORDINATE" : 359807.0,
      "Y_COORDINATE" : 178376.0,
      "STATUS" : "APPROVED",
      "LOGICAL_STATUS_CODE" : "1",
      "CLASSIFICATION_CODE" : "RD04",
      "CLASSIFICATION_CODE_DESCRIPTION" : "Terraced",
      "LOCAL_CUSTODIAN_CODE" : 119,
      "LOCAL_CUSTODIAN_CODE_DESCRIPTION" : "SOUTH GLOUCESTERSHIRE",
      "POSTAL_ADDRESS_CODE" : "D",
      "POSTAL_ADDRESS_CODE_DESCRIPTION" : "A record which is linked to PAF",
      "BLPU_STATE_CODE" : "2",
      "BLPU_STATE_CODE_DESCRIPTION" : "In use",
      "TOPOGRAPHY_LAYER_TOID" : "osgb1000015017309",
      "LAST_UPDATE_DATE" : "24/04/2019",
      "ENTRY_DATE" : "01/04/1999",
      "BLPU_STATE_DATE" : "01/12/2011",
      "LANGUAGE" : "EN",
      "MATCH" : 1.0,
      "MATCH_DESCRIPTION" : "EXACT"
    }
  }, {
    "DPA" : {
      "UPRN" : "500559",
      "UDPRN" : "2764580",
      "ADDRESS" : "14, BRONCKSEA ROAD, BRISTOL, BS7 0SE",
      "BUILDING_NUMBER" : "14",
      "THOROUGHFARE_NAME" : "BRONCKSEA ROAD",
      "POST_TOWN" : "BRISTOL",
      "POSTCODE" : "BS7 0SE",
      "RPC" : "1",
      "X_COORDINATE" : 359798.0,
      "Y_COORDINATE" : 178420.0,
      "STATUS" : "APPROVED",
      "LOGICAL_STATUS_CODE" : "1",
      "CLASSIFICATION_CODE" : "RD02",
      "CLASSIFICATION_CODE_DESCRIPTION" : "Detached",
      "LOCAL_CUSTODIAN_CODE" : 119,
      "LOCAL_CUSTODIAN_CODE_DESCRIPTION" : "SOUTH GLOUCESTERSHIRE",
      "POSTAL_ADDRESS_CODE" : "D",
      "POSTAL_ADDRESS_CODE_DESCRIPTION" : "A record which is linked to PAF",
      "BLPU_STATE_CODE" : "2",
      "BLPU_STATE_CODE_DESCRIPTION" : "In use",
      "TOPOGRAPHY_LAYER_TOID" : "osgb1000015017357",
      "LAST_UPDATE_DATE" : "24/04/2019",
      "ENTRY_DATE" : "01/04/1999",
      "BLPU_STATE_DATE" : "01/12/2011",
      "LANGUAGE" : "EN",
      "MATCH" : 1.0,
      "MATCH_DESCRIPTION" : "EXACT"
    }
  }, {
    "DPA" : {
      "UPRN" : "500560",
      "UDPRN" : "2764581",
      "ADDRESS" : "15, BRONCKSEA ROAD, BRISTOL, BS7 0SE",
      "BUILDING_NUMBER" : "15",
      "THOROUGHFARE_NAME" : "BRONCKSEA ROAD",
      "POST_TOWN" : "BRISTOL",
      "POSTCODE" : "BS7 0SE",
      "RPC" : "2",
      "X_COORDINATE" : 359793.0,
      "Y_COORDINATE" : 178381.0,
      "STATUS" : "APPROVED",
      "LOGICAL_STATUS_CODE" : "1",
      "CLASSIFICATION_CODE" : "RD03",
      "CLASSIFICATION_CODE_DESCRIPTION" : "Semi-Detached",
      "LOCAL_CUSTODIAN_CODE" : 119,
      "LOCAL_CUSTODIAN_CODE_DESCRIPTION" : "SOUTH GLOUCESTERSHIRE",
      "POSTAL_ADDRESS_CODE" : "D",
      "POSTAL_ADDRESS_CODE_DESCRIPTION" : "A record which is linked to PAF",
      "BLPU_STATE_CODE" : "2",
      "BLPU_STATE_CODE_DESCRIPTION" : "In use",
      "TOPOGRAPHY_LAYER_TOID" : "osgb1000015017313",
      "LAST_UPDATE_DATE" : "24/04/2019",
      "ENTRY_DATE" : "01/04/1999",
      "BLPU_STATE_DATE" : "01/12/2011",
      "LANGUAGE" : "EN",
      "MATCH" : 1.0,
      "MATCH_DESCRIPTION" : "EXACT"
    }
  }, {
    "DPA" : {
      "UPRN" : "500561",
      "UDPRN" : "2764582",
      "ADDRESS" : "16, BRONCKSEA ROAD, BRISTOL, BS7 0SE",
      "BUILDING_NUMBER" : "16",
      "THOROUGHFARE_NAME" : "BRONCKSEA ROAD",
      "POST_TOWN" : "BRISTOL",
      "POSTCODE" : "BS7 0SE",
      "RPC" : "2",
      "X_COORDINATE" : 359784.0,
      "Y_COORDINATE" : 178422.0,
      "STATUS" : "APPROVED",
      "LOGICAL_STATUS_CODE" : "1",
      "CLASSIFICATION_CODE" : "RD02",
      "CLASSIFICATION_CODE_DESCRIPTION" : "Detached",
      "LOCAL_CUSTODIAN_CODE" : 119,
      "LOCAL_CUSTODIAN_CODE_DESCRIPTION" : "SOUTH GLOUCESTERSHIRE",
      "POSTAL_ADDRESS_CODE" : "D",
      "POSTAL_ADDRESS_CODE_DESCRIPTION" : "A record which is linked to PAF",
      "BLPU_STATE_CODE" : "2",
      "BLPU_STATE_CODE_DESCRIPTION" : "In use",
      "TOPOGRAPHY_LAYER_TOID" : "osgb1000015017359",
      "LAST_UPDATE_DATE" : "24/04/2019",
      "ENTRY_DATE" : "01/04/1999",
      "BLPU_STATE_DATE" : "01/12/2011",
      "LANGUAGE" : "EN",
      "MATCH" : 1.0,
      "MATCH_DESCRIPTION" : "EXACT"
    }
  }, {
    "DPA" : {
      "UPRN" : "500562",
      "UDPRN" : "2764583",
      "ADDRESS" : "17, BRONCKSEA ROAD, BRISTOL, BS7 0SE",
      "BUILDING_NUMBER" : "17",
      "THOROUGHFARE_NAME" : "BRONCKSEA ROAD",
      "POST_TOWN" : "BRISTOL",
      "POSTCODE" : "BS7 0SE",
      "RPC" : "1",
      "X_COORDINATE" : 359785.0,
      "Y_COORDINATE" : 178384.0,
      "STATUS" : "APPROVED",
      "LOGICAL_STATUS_CODE" : "1",
      "CLASSIFICATION_CODE" : "RD03",
      "CLASSIFICATION_CODE_DESCRIPTION" : "Semi-Detached",
      "LOCAL_CUSTODIAN_CODE" : 119,
      "LOCAL_CUSTODIAN_CODE_DESCRIPTION" : "SOUTH GLOUCESTERSHIRE",
      "POSTAL_ADDRESS_CODE" : "D",
      "POSTAL_ADDRESS_CODE_DESCRIPTION" : "A record which is linked to PAF",
      "BLPU_STATE_CODE" : "2",
      "BLPU_STATE_CODE_DESCRIPTION" : "In use",
      "TOPOGRAPHY_LAYER_TOID" : "osgb1000015017314",
      "LAST_UPDATE_DATE" : "24/04/2019",
      "ENTRY_DATE" : "01/04/1999",
      "BLPU_STATE_DATE" : "01/12/2011",
      "LANGUAGE" : "EN",
      "MATCH" : 1.0,
      "MATCH_DESCRIPTION" : "EXACT"
    }
  }, {
    "DPA" : {
      "UPRN" : "500563",
      "UDPRN" : "2764584",
      "ADDRESS" : "18, BRONCKSEA ROAD, BRISTOL, BS7 0SE",
      "BUILDING_NUMBER" : "18",
      "THOROUGHFARE_NAME" : "BRONCKSEA ROAD",
      "POST_TOWN" : "BRISTOL",
      "POSTCODE" : "BS7 0SE",
      "RPC" : "2",
      "X_COORDINATE" : 359772.0,
      "Y_COORDINATE" : 178420.0,
      "STATUS" : "APPROVED",
      "LOGICAL_STATUS_CODE" : "1",
      "CLASSIFICATION_CODE" : "RD02",
      "CLASSIFICATION_CODE_DESCRIPTION" : "Detached",
      "LOCAL_CUSTODIAN_CODE" : 119,
      "LOCAL_CUSTODIAN_CODE_DESCRIPTION" : "SOUTH GLOUCESTERSHIRE",
      "POSTAL_ADDRESS_CODE" : "D",
      "POSTAL_ADDRESS_CODE_DESCRIPTION" : "A record which is linked to PAF",
      "BLPU_STATE_CODE" : "2",
      "BLPU_STATE_CODE_DESCRIPTION" : "In use",
      "TOPOGRAPHY_LAYER_TOID" : "osgb1000015017361",
      "LAST_UPDATE_DATE" : "24/04/2019",
      "ENTRY_DATE" : "01/04/1999",
      "BLPU_STATE_DATE" : "01/12/2011",
      "LANGUAGE" : "EN",
      "MATCH" : 1.0,
      "MATCH_DESCRIPTION" : "EXACT"
    }
  }, {
    "DPA" : {
      "UPRN" : "500564",
      "UDPRN" : "2764585",
      "ADDRESS" : "19, BRONCKSEA ROAD, BRISTOL, BS7 0SE",
      "BUILDING_NUMBER" : "19",
      "THOROUGHFARE_NAME" : "BRONCKSEA ROAD",
      "POST_TOWN" : "BRISTOL",
      "POSTCODE" : "BS7 0SE",
      "RPC" : "1",
      "X_COORDINATE" : 359769.0,
      "Y_COORDINATE" : 178385.0,
      "STATUS" : "APPROVED",
      "LOGICAL_STATUS_CODE" : "1",
      "CLASSIFICATION_CODE" : "RD03",
      "CLASSIFICATION_CODE_DESCRIPTION" : "Semi-Detached",
      "LOCAL_CUSTODIAN_CODE" : 119,
      "LOCAL_CUSTODIAN_CODE_DESCRIPTION" : "SOUTH GLOUCESTERSHIRE",
      "POSTAL_ADDRESS_CODE" : "D",
      "POSTAL_ADDRESS_CODE_DESCRIPTION" : "A record which is linked to PAF",
      "BLPU_STATE_CODE" : "2",
      "BLPU_STATE_CODE_DESCRIPTION" : "In use",
      "TOPOGRAPHY_LAYER_TOID" : "osgb1000015017317",
      "LAST_UPDATE_DATE" : "24/04/2019",
      "ENTRY_DATE" : "01/04/1999",
      "BLPU_STATE_DATE" : "01/12/2011",
      "LANGUAGE" : "EN",
      "MATCH" : 1.0,
      "MATCH_DESCRIPTION" : "EXACT"
    }
  }, {
    "DPA" : {
      "UPRN" : "500566",
      "UDPRN" : "2764587",
      "ADDRESS" : "20, BRONCKSEA ROAD, BRISTOL, BS7 0SE",
      "BUILDING_NUMBER" : "20",
      "THOROUGHFARE_NAME" : "BRONCKSEA ROAD",
      "POST_TOWN" : "BRISTOL",
      "POSTCODE" : "BS7 0SE",
      "RPC" : "2",
      "X_COORDINATE" : 359761.84,
      "Y_COORDINATE" : 178428.55,
      "STATUS" : "APPROVED",
      "LOGICAL_STATUS_CODE" : "1",
      "CLASSIFICATION_CODE" : "RD02",
      "CLASSIFICATION_CODE_DESCRIPTION" : "Detached",
      "LOCAL_CUSTODIAN_CODE" : 119,
      "LOCAL_CUSTODIAN_CODE_DESCRIPTION" : "SOUTH GLOUCESTERSHIRE",
      "POSTAL_ADDRESS_CODE" : "D",
      "POSTAL_ADDRESS_CODE_DESCRIPTION" : "A record which is linked to PAF",
      "BLPU_STATE_CODE" : "2",
      "BLPU_STATE_CODE_DESCRIPTION" : "In use",
      "TOPOGRAPHY_LAYER_TOID" : "osgb1000015017363",
      "LAST_UPDATE_DATE" : "24/04/2019",
      "ENTRY_DATE" : "01/04/1999",
      "BLPU_STATE_DATE" : "01/12/2011",
      "LANGUAGE" : "EN",
      "MATCH" : 1.0,
      "MATCH_DESCRIPTION" : "EXACT"
    }
  }, {
    "DPA" : {
      "UPRN" : "500567",
      "UDPRN" : "2764588",
      "ADDRESS" : "21, BRONCKSEA ROAD, BRISTOL, BS7 0SE",
      "BUILDING_NUMBER" : "21",
      "THOROUGHFARE_NAME" : "BRONCKSEA ROAD",
      "POST_TOWN" : "BRISTOL",
      "POSTCODE" : "BS7 0SE",
      "RPC" : "1",
      "X_COORDINATE" : 359763.0,
      "Y_COORDINATE" : 178387.0,
      "STATUS" : "APPROVED",
      "LOGICAL_STATUS_CODE" : "1",
      "CLASSIFICATION_CODE" : "RD03",
      "CLASSIFICATION_CODE_DESCRIPTION" : "Semi-Detached",
      "LOCAL_CUSTODIAN_CODE" : 119,
      "LOCAL_CUSTODIAN_CODE_DESCRIPTION" : "SOUTH GLOUCESTERSHIRE",
      "POSTAL_ADDRESS_CODE" : "D",
      "POSTAL_ADDRESS_CODE_DESCRIPTION" : "A record which is linked to PAF",
      "BLPU_STATE_CODE" : "2",
      "BLPU_STATE_CODE_DESCRIPTION" : "In use",
      "TOPOGRAPHY_LAYER_TOID" : "osgb1000015017318",
      "LAST_UPDATE_DATE" : "24/04/2019",
      "ENTRY_DATE" : "01/04/1999",
      "BLPU_STATE_DATE" : "01/12/2011",
      "LANGUAGE" : "EN",
      "MATCH" : 1.0,
      "MATCH_DESCRIPTION" : "EXACT"
    }
  }, {
    "DPA" : {
      "UPRN" : "500568",
      "UDPRN" : "2764589",
      "ADDRESS" : "23, BRONCKSEA ROAD, BRISTOL, BS7 0SE",
      "BUILDING_NUMBER" : "23",
      "THOROUGHFARE_NAME" : "BRONCKSEA ROAD",
      "POST_TOWN" : "BRISTOL",
      "POSTCODE" : "BS7 0SE",
      "RPC" : "2",
      "X_COORDINATE" : 359749.0,
      "Y_COORDINATE" : 178391.0,
      "STATUS" : "APPROVED",
      "LOGICAL_STATUS_CODE" : "1",
      "CLASSIFICATION_CODE" : "RD03",
      "CLASSIFICATION_CODE_DESCRIPTION" : "Semi-Detached",
      "LOCAL_CUSTODIAN_CODE" : 119,
      "LOCAL_CUSTODIAN_CODE_DESCRIPTION" : "SOUTH GLOUCESTERSHIRE",
      "POSTAL_ADDRESS_CODE" : "D",
      "POSTAL_ADDRESS_CODE_DESCRIPTION" : "A record which is linked to PAF",
      "BLPU_STATE_CODE" : "2",
      "BLPU_STATE_CODE_DESCRIPTION" : "In use",
      "TOPOGRAPHY_LAYER_TOID" : "osgb1000015017321",
      "LAST_UPDATE_DATE" : "24/04/2019",
      "ENTRY_DATE" : "01/04/1999",
      "BLPU_STATE_DATE" : "01/12/2011",
      "LANGUAGE" : "EN",
      "MATCH" : 1.0,
      "MATCH_DESCRIPTION" : "EXACT"
    }
  }, {
    "DPA" : {
      "UPRN" : "500569",
      "UDPRN" : "2764590",
      "ADDRESS" : "25, BRONCKSEA ROAD, BRISTOL, BS7 0SE",
      "BUILDING_NUMBER" : "25",
      "THOROUGHFARE_NAME" : "BRONCKSEA ROAD",
      "POST_TOWN" : "BRISTOL",
      "POSTCODE" : "BS7 0SE",
      "RPC" : "1",
      "X_COORDINATE" : 359741.0,
      "Y_COORDINATE" : 178392.0,
      "STATUS" : "APPROVED",
      "LOGICAL_STATUS_CODE" : "1",
      "CLASSIFICATION_CODE" : "RD03",
      "CLASSIFICATION_CODE_DESCRIPTION" : "Semi-Detached",
      "LOCAL_CUSTODIAN_CODE" : 119,
      "LOCAL_CUSTODIAN_CODE_DESCRIPTION" : "SOUTH GLOUCESTERSHIRE",
      "POSTAL_ADDRESS_CODE" : "D",
      "POSTAL_ADDRESS_CODE_DESCRIPTION" : "A record which is linked to PAF",
      "BLPU_STATE_CODE" : "2",
      "BLPU_STATE_CODE_DESCRIPTION" : "In use",
      "TOPOGRAPHY_LAYER_TOID" : "osgb1000015017322",
      "LAST_UPDATE_DATE" : "24/04/2019",
      "ENTRY_DATE" : "01/04/1999",
      "BLPU_STATE_DATE" : "01/12/2011",
      "LANGUAGE" : "EN",
      "MATCH" : 1.0,
      "MATCH_DESCRIPTION" : "EXACT"
    }
  }, {
    "DPA" : {
      "UPRN" : "665719",
      "UDPRN" : "52516034",
      "ADDRESS" : "13A, BRONCKSEA ROAD, BRISTOL, BS7 0SE",
      "BUILDING_NAME" : "13A",
      "THOROUGHFARE_NAME" : "BRONCKSEA ROAD",
      "POST_TOWN" : "BRISTOL",
      "POSTCODE" : "BS7 0SE",
      "RPC" : "2",
      "X_COORDINATE" : 359792.0,
      "Y_COORDINATE" : 178332.0,
      "STATUS" : "APPROVED",
      "LOGICAL_STATUS_CODE" : "1",
      "CLASSIFICATION_CODE" : "RD02",
      "CLASSIFICATION_CODE_DESCRIPTION" : "Detached",
      "LOCAL_CUSTODIAN_CODE" : 119,
      "LOCAL_CUSTODIAN_CODE_DESCRIPTION" : "SOUTH GLOUCESTERSHIRE",
      "POSTAL_ADDRESS_CODE" : "D",
      "POSTAL_ADDRESS_CODE_DESCRIPTION" : "A record which is linked to PAF",
      "BLPU_STATE_CODE" : "2",
      "BLPU_STATE_CODE_DESCRIPTION" : "In use",
      "TOPOGRAPHY_LAYER_TOID" : "osgb5000005120622029",
      "LAST_UPDATE_DATE" : "24/04/2019",
      "ENTRY_DATE" : "30/08/2011",
      "BLPU_STATE_DATE" : "30/08/2011",
      "LANGUAGE" : "EN",
      "MATCH" : 1.0,
      "MATCH_DESCRIPTION" : "EXACT"
    }
  }, {
    "DPA" : {
      "UPRN" : "674320",
      "UDPRN" : "54458741",
      "ADDRESS" : "2A, BRONCKSEA ROAD, BRISTOL, BS7 0SE",
      "BUILDING_NAME" : "2A",
      "THOROUGHFARE_NAME" : "BRONCKSEA ROAD",
      "POST_TOWN" : "BRISTOL",
      "POSTCODE" : "BS7 0SE",
      "RPC" : "1",
      "X_COORDINATE" : 359881.1,
      "Y_COORDINATE" : 178385.42,
      "STATUS" : "APPROVED",
      "LOGICAL_STATUS_CODE" : "1",
      "CLASSIFICATION_CODE" : "RD03",
      "CLASSIFICATION_CODE_DESCRIPTION" : "Semi-Detached",
      "LOCAL_CUSTODIAN_CODE" : 119,
      "LOCAL_CUSTODIAN_CODE_DESCRIPTION" : "SOUTH GLOUCESTERSHIRE",
      "POSTAL_ADDRESS_CODE" : "D",
      "POSTAL_ADDRESS_CODE_DESCRIPTION" : "A record which is linked to PAF",
      "BLPU_STATE_CODE" : "2",
      "BLPU_STATE_CODE_DESCRIPTION" : "In use",
      "TOPOGRAPHY_LAYER_TOID" : "osgb5000005205571146",
      "LAST_UPDATE_DATE" : "24/04/2019",
      "ENTRY_DATE" : "30/08/2016",
      "BLPU_STATE_DATE" : "02/05/2017",
      "LANGUAGE" : "EN",
      "MATCH" : 1.0,
      "MATCH_DESCRIPTION" : "EXACT"
    }
  }, {
    "DPA" : {
      "UPRN" : "674321",
      "UDPRN" : "54458743",
      "ADDRESS" : "2B, BRONCKSEA ROAD, BRISTOL, BS7 0SE",
      "BUILDING_NAME" : "2B",
      "THOROUGHFARE_NAME" : "BRONCKSEA ROAD",
      "POST_TOWN" : "BRISTOL",
      "POSTCODE" : "BS7 0SE",
      "RPC" : "1",
      "X_COORDINATE" : 359886.69,
      "Y_COORDINATE" : 178383.12,
      "STATUS" : "APPROVED",
      "LOGICAL_STATUS_CODE" : "1",
      "CLASSIFICATION_CODE" : "RD03",
      "CLASSIFICATION_CODE_DESCRIPTION" : "Semi-Detached",
      "LOCAL_CUSTODIAN_CODE" : 119,
      "LOCAL_CUSTODIAN_CODE_DESCRIPTION" : "SOUTH GLOUCESTERSHIRE",
      "POSTAL_ADDRESS_CODE" : "D",
      "POSTAL_ADDRESS_CODE_DESCRIPTION" : "A record which is linked to PAF",
      "BLPU_STATE_CODE" : "2",
      "BLPU_STATE_CODE_DESCRIPTION" : "In use",
      "TOPOGRAPHY_LAYER_TOID" : "osgb5000005205571145",
      "LAST_UPDATE_DATE" : "24/04/2019",
      "ENTRY_DATE" : "30/08/2016",
      "BLPU_STATE_DATE" : "02/05/2017",
      "LANGUAGE" : "EN",
      "MATCH" : 1.0,
      "MATCH_DESCRIPTION" : "EXACT"
    }
  }, {
    "DPA" : {
      "UPRN" : "500795",
      "UDPRN" : "2764592",
      "ADDRESS" : "3A, BRONCKSEA ROAD, BRISTOL, BS7 0SE",
      "BUILDING_NAME" : "3A",
      "THOROUGHFARE_NAME" : "BRONCKSEA ROAD",
      "POST_TOWN" : "BRISTOL",
      "POSTCODE" : "BS7 0SE",
      "RPC" : "1",
      "X_COORDINATE" : 359846.0,
      "Y_COORDINATE" : 178362.0,
      "STATUS" : "APPROVED",
      "LOGICAL_STATUS_CODE" : "1",
      "CLASSIFICATION_CODE" : "RD03",
      "CLASSIFICATION_CODE_DESCRIPTION" : "Semi-Detached",
      "LOCAL_CUSTODIAN_CODE" : 119,
      "LOCAL_CUSTODIAN_CODE_DESCRIPTION" : "SOUTH GLOUCESTERSHIRE",
      "POSTAL_ADDRESS_CODE" : "D",
      "POSTAL_ADDRESS_CODE_DESCRIPTION" : "A record which is linked to PAF",
      "BLPU_STATE_CODE" : "2",
      "BLPU_STATE_CODE_DESCRIPTION" : "In use",
      "TOPOGRAPHY_LAYER_TOID" : "osgb1000015017298",
      "LAST_UPDATE_DATE" : "24/04/2019",
      "ENTRY_DATE" : "01/04/1999",
      "BLPU_STATE_DATE" : "01/12/2011",
      "LANGUAGE" : "EN",
      "MATCH" : 1.0,
      "MATCH_DESCRIPTION" : "EXACT"
    }
  } ]
}
