{
  "header" : {
    "uri" : "https://api.ordnancesurvey.co.uk/places/v1/addresses/postcode?postcode=L14AR",
    "query" : "postcode=L14AR",
    "offset" : 0,
    "totalresults" : 64,
    "format" : "JSON",
    "dataset" : "DPA",
    "lr" : "EN,CY",
    "maxresults" : 100,
    "epoch" : "69",
    "output_srs" : "EPSG:27700"
  },
  "results" : [ {
    "DPA" : {
      "UPRN" : "38057460",
      "UDPRN" : "12489030",
      "ADDRESS" : "5, FLEET STREET, LIVERPOOL, L1 4AR",
      "BUILDING_NUMBER" : "5",
      "THOROUGHFARE_NAME" : "FLEET STREET",
      "POST_TOWN" : "LIVERPOOL",
      "POSTCODE" : "L1 4AR",
      "RPC" : "1",
      "X_COORDINATE" : 334826.0,
      "Y_COORDINATE" : 390134.0,
      "STATUS" : "APPROVED",
      "LOGICAL_STATUS_CODE" : "1",
      "CLASSIFICATION_CODE" : "CR06",
      "CLASSIFICATION_CODE_DESCRIPTION" : "Public House / Bar / Nightclub",
      "LOCAL_CUSTODIAN_CODE" : 4310,
      "LOCAL_CUSTODIAN_CODE_DESCRIPTION" : "LIVERPOOL",
      "POSTAL_ADDRESS_CODE" : "D",
      "POSTAL_ADDRESS_CODE_DESCRIPTION" : "A record which is linked to PAF",
      "BLPU_STATE_CODE" : "2",
      "BLPU_STATE_CODE_DESCRIPTION" : "In use",
      "TOPOGRAPHY_LAYER_TOID" : "osgb1000034933533",
      "LAST_UPDATE_DATE" : "10/02/2016",
      "ENTRY_DATE" : "11/05/1999",
      "BLPU_STATE_DATE" : "18/02/2011",
      "LANGUAGE" : "EN",
      "MATCH" : 1.0,
      "MATCH_DESCRIPTION" : "EXACT"
    }
  }, {
    "DPA" : {
      "UPRN" : "38290189",
      "UDPRN" : "12489017",
      "ADDRESS" : "9, FLEET STREET, LIVERPOOL, L1 4AR",
      "BUILDING_NUMBER" : "9",
      "THOROUGHFARE_NAME" : "FLEET STREET",
      "POST_TOWN" : "LIVERPOOL",
      "POSTCODE" : "L1 4AR",
      "RPC" : "1",
      "X_COORDINATE" : 334834.0,
      "Y_COORDINATE" : 390128.0,
      "STATUS" : "APPROVED",
      "LOGICAL_STATUS_CODE" : "1",
      "CLASSIFICATION_CODE" : "CO01",
      "CLASSIFICATION_CODE_DESCRIPTION" : "Office / Work Studio",
      "LOCAL_CUSTODIAN_CODE" : 4310,
      "LOCAL_CUSTODIAN_CODE_DESCRIPTION" : "LIVERPOOL",
      "POSTAL_ADDRESS_CODE" : "D",
      "POSTAL_ADDRESS_CODE_DESCRIPTION" : "A record which is linked to PAF",
      "BLPU_STATE_CODE" : null,
      "BLPU_STATE_CODE_DESCRIPTION" : "Unknown/Not applicable",
      "TOPOGRAPHY_LAYER_TOID" : "osgb1000034933532",
      "LAST_UPDATE_DATE" : "10/02/2016",
      "ENTRY_DATE" : "03/09/2010",
      "LANGUAGE" : "EN",
      "MATCH" : 1.0,
      "MATCH_DESCRIPTION" : "EXACT"
    }
  }, {
    "DPA" : {
      "UPRN" : "38057463",
      "UDPRN" : "12489024",
      "ADDRESS" : "17, FLEET STREET, LIVERPOOL, L1 4AR",
      "BUILDING_NUMBER" : "17",
      "THOROUGHFARE_NAME" : "FLEET STREET",
      "POST_TOWN" : "LIVERPOOL",
      "POSTCODE" : "L1 4AR",
      "RPC" : "1",
      "X_COORDINATE" : 334877.0,
      "Y_COORDINATE" : 390092.0,
      "STATUS" : "HISTORICAL",
      "LOGICAL_STATUS_CODE" : "8",
      "CLASSIFICATION_CODE" : "CL01",
      "CLASSIFICATION_CODE_DESCRIPTION" : "Amusements",
      "LOCAL_CUSTODIAN_CODE" : 4310,
      "LOCAL_CUSTODIAN_CODE_DESCRIPTION" : "LIVERPOOL",
      "POSTAL_ADDRESS_CODE" : "D",
      "POSTAL_ADDRESS_CODE_DESCRIPTION" : "A record which is linked to PAF",
      "BLPU_STATE_CODE" : null,
      "BLPU_STATE_CODE_DESCRIPTION" : "Unknown/Not applicable",
      "TOPOGRAPHY_LAYER_TOID" : "osgb1000034933420",
      "LAST_UPDATE_DATE" : "01/01/2017",
      "ENTRY_DATE" : "01/07/1998",
      "LANGUAGE" : "EN",
      "MATCH" : 1.0,
      "MATCH_DESCRIPTION" : "EXACT"
    }
  }, {
    "DPA" : {
      "UPRN" : "38291667",
      "UDPRN" : "12489018",
      "ADDRESS" : "27, FLEET STREET, LIVERPOOL, L1 4AR",
      "BUILDING_NUMBER" : "27",
      "THOROUGHFARE_NAME" : "FLEET STREET",
      "POST_TOWN" : "LIVERPOOL",
      "POSTCODE" : "L1 4AR",
      "RPC" : "2",
      "X_COORDINATE" : 334882.75,
      "Y_COORDINATE" : 390077.66,
      "STATUS" : "APPROVED",
      "LOGICAL_STATUS_CODE" : "1",
      "CLASSIFICATION_CODE" : "C",
      "CLASSIFICATION_CODE_DESCRIPTION" : "Commercial",
      "LOCAL_CUSTODIAN_CODE" : 4310,
      "LOCAL_CUSTODIAN_CODE_DESCRIPTION" : "LIVERPOOL",
      "POSTAL_ADDRESS_CODE" : "D",
      "POSTAL_ADDRESS_CODE_DESCRIPTION" : "A record which is linked to PAF",
      "BLPU_STATE_CODE" : null,
      "BLPU_STATE_CODE_DESCRIPTION" : "Unknown/Not applicable",
      "TOPOGRAPHY_LAYER_TOID" : "osgb1000034933439",
      "LAST_UPDATE_DATE" : "12/11/2018",
      "ENTRY_DATE" : "21/04/2011",
      "LANGUAGE" : "EN",
      "MATCH" : 1.0,
      "MATCH_DESCRIPTION" : "EXACT"
    }
  }, {
    "DPA" : {
      "UPRN" : "38209196",
      "UDPRN" : "12489019",
      "ADDRESS" : "10, CONCERT SQUARE APARTMENTS, 29, FLEET STREET, LIVERPOOL, L1 4AR",
      "SUB_BUILDING_NAME" : "10",
      "BUILDING_NAME" : "CONCERT SQUARE APARTMENTS",
      "BUILDING_NUMBER" : "29",
      "THOROUGHFARE_NAME" : "FLEET STREET",
      "POST_TOWN" : "LIVERPOOL",
      "POSTCODE" : "L1 4AR",
      "RPC" : "2",
      "X_COORDINATE" : 334893.0,
      "Y_COORDINATE" : 390069.0,
      "STATUS" : "APPROVED",
      "LOGICAL_STATUS_CODE" : "1",
      "CLASSIFICATION_CODE" : "RD06",
      "CLASSIFICATION_CODE_DESCRIPTION" : "Self Contained Flat (Includes Maisonette / Apartment)",
      "LOCAL_CUSTODIAN_CODE" : 4310,
      "LOCAL_CUSTODIAN_CODE_DESCRIPTION" : "LIVERPOOL",
      "POSTAL_ADDRESS_CODE" : "D",
      "POSTAL_ADDRESS_CODE_DESCRIPTION" : "A record which is linked to PAF",
      "BLPU_STATE_CODE" : null,
      "BLPU_STATE_CODE_DESCRIPTION" : "Unknown/Not applicable",
      "TOPOGRAPHY_LAYER_TOID" : "osgb1000034933439",
      "PARENT_UPRN" : "38209195",
      "LAST_UPDATE_DATE" : "12/11/2018",
      "ENTRY_DATE" : "07/07/1997",
      "LANGUAGE" : "EN",
      "MATCH" : 1.0,
      "MATCH_DESCRIPTION" : "EXACT"
    }
  }, {
    "DPA" : {
      "UPRN" : "38209197",
      "UDPRN" : "12489020",
      "ADDRESS" : "11, CONCERT SQUARE APARTMENTS, 29, FLEET STREET, LIVERPOOL, L1 4AR",
      "SUB_BUILDING_NAME" : "11",
      "BUILDING_NAME" : "CONCERT SQUARE APARTMENTS",
      "BUILDING_NUMBER" : "29",
      "THOROUGHFARE_NAME" : "FLEET STREET",
      "POST_TOWN" : "LIVERPOOL",
      "POSTCODE" : "L1 4AR",
      "RPC" : "2",
      "X_COORDINATE" : 334893.0,
      "Y_COORDINATE" : 390069.0,
      "STATUS" : "APPROVED",
      "LOGICAL_STATUS_CODE" : "1",
      "CLASSIFICATION_CODE" : "RD06",
      "CLASSIFICATION_CODE_DESCRIPTION" : "Self Contained Flat (Includes Maisonette / Apartment)",
      "LOCAL_CUSTODIAN_CODE" : 4310,
      "LOCAL_CUSTODIAN_CODE_DESCRIPTION" : "LIVERPOOL",
      "POSTAL_ADDRESS_CODE" : "D",
      "POSTAL_ADDRESS_CODE_DESCRIPTION" : "A record which is linked to PAF",
      "BLPU_STATE_CODE" : null,
      "BLPU_STATE_CODE_DESCRIPTION" : "Unknown/Not applicable",
      "TOPOGRAPHY_LAYER_TOID" : "osgb1000034933439",
      "PARENT_UPRN" : "38209195",
      "LAST_UPDATE_DATE" : "12/11/2018",
      "ENTRY_DATE" : "07/07/1997",
      "LANGUAGE" : "EN",
      "MATCH" : 1.0,
      "MATCH_DESCRIPTION" : "EXACT"
    }
  }, {
    "DPA" : {
      "UPRN" : "38209198",
      "UDPRN" : "12489021",
      "ADDRESS" : "12, CONCERT SQUARE APARTMENTS, 29, FLEET STREET, LIVERPOOL, L1 4AR",
      "SUB_BUILDING_NAME" : "12",
      "BUILDING_NAME" : "CONCERT SQUARE APARTMENTS",
      "BUILDING_NUMBER" : "29",
      "THOROUGHFARE_NAME" : "FLEET STREET",
      "POST_TOWN" : "LIVERPOOL",
      "POSTCODE" : "L1 4AR",
      "RPC" : "2",
      "X_COORDINATE" : 334893.0,
      "Y_COORDINATE" : 390069.0,
      "STATUS" : "APPROVED",
      "LOGICAL_STATUS_CODE" : "1",
      "CLASSIFICATION_CODE" : "RD06",
      "CLASSIFICATION_CODE_DESCRIPTION" : "Self Contained Flat (Includes Maisonette / Apartment)",
      "LOCAL_CUSTODIAN_CODE" : 4310,
      "LOCAL_CUSTODIAN_CODE_DESCRIPTION" : "LIVERPOOL",
      "POSTAL_ADDRESS_CODE" : "D",
      "POSTAL_ADDRESS_CODE_DESCRIPTION" : "A record which is linked to PAF",
      "BLPU_STATE_CODE" : null,
      "BLPU_STATE_CODE_DESCRIPTION" : "Unknown/Not applicable",
      "TOPOGRAPHY_LAYER_TOID" : "osgb1000034933439",
      "PARENT_UPRN" : "38209195",
      "LAST_UPDATE_DATE" : "12/11/2018",
      "ENTRY_DATE" : "07/07/1997",
      "LANGUAGE" : "EN",
      "MATCH" : 1.0,
      "MATCH_DESCRIPTION" : "EXACT"
    }
  }, {
    "DPA" : {
      "UPRN" : "38209199",
      "UDPRN" : "12489022",
      "ADDRESS" : "13, CONCERT SQUARE APARTMENTS, 29, FLEET STREET, LIVERPOOL, L1 4AR",
      "SUB_BUILDING_NAME" : "13",
      "BUILDING_NAME" : "CONCERT SQUARE APARTMENTS",
      "BUILDING_NUMBER" : "29",
      "THOROUGHFARE_NAME" : "FLEET STREET",
      "POST_TOWN" : "LIVERPOOL",
      "POSTCODE" : "L1 4AR",
      "RPC" : "2",
      "X_COORDINATE" : 334893.0,
      "Y_COORDINATE" : 390069.0,
      "STATUS" : "APPROVED",
      "LOGICAL_STATUS_CODE" : "1",
      "CLASSIFICATION_CODE" : "RD06",
      "CLASSIFICATION_CODE_DESCRIPTION" : "Self Contained Flat (Includes Maisonette / Apartment)",
      "LOCAL_CUSTODIAN_CODE" : 4310,
      "LOCAL_CUSTODIAN_CODE_DESCRIPTION" : "LIVERPOOL",
      "POSTAL_ADDRESS_CODE" : "D",
      "POSTAL_ADDRESS_CODE_DESCRIPTION" : "A record which is linked to PAF",
      "BLPU_STATE_CODE" : null,
      "BLPU_STATE_CODE_DESCRIPTION" : "Unknown/Not applicable",
      "TOPOGRAPHY_LAYER_TOID" : "osgb1000034933439",
      "PARENT_UPRN" : "38209195",
      "LAST_UPDATE_DATE" : "12/11/2018",
      "ENTRY_DATE" : "07/07/1997",
      "LANGUAGE" : "EN",
      "MATCH" : 1.0,
      "MATCH_DESCRIPTION" : "EXACT"
    }
  }, {
    "DPA" : {
      "UPRN" : "38209200",
      "UDPRN" : "12489023",
      "ADDRESS" : "14, CONCERT SQUARE APARTMENTS, 29, FLEET STREET, LIVERPOOL, L1 4AR",
      "SUB_BUILDING_NAME" : "14",
      "BUILDING_NAME" : "CONCERT SQUARE APARTMENTS",
      "BUILDING_NUMBER" : "29",
      "THOROUGHFARE_NAME" : "FLEET STREET",
      "POST_TOWN" : "LIVERPOOL",
      "POSTCODE" : "L1 4AR",
      "RPC" : "2",
      "X_COORDINATE" : 334893.0,
      "Y_COORDINATE" : 390069.0,
      "STATUS" : "APPROVED",
      "LOGICAL_STATUS_CODE" : "1",
      "CLASSIFICATION_CODE" : "RD06",
      "CLASSIFICATION_CODE_DESCRIPTION" : "Self Contained Flat (Includes Maisonette / Apartment)",
      "LOCAL_CUSTODIAN_CODE" : 4310,
      "LOCAL_CUSTODIAN_CODE_DESCRIPTION" : "LIVERPOOL",
      "POSTAL_ADDRESS_CODE" : "D",
      "POSTAL_ADDRESS_CODE_DESCRIPTION" : "A record which is linked to PAF",
      "BLPU_STATE_CODE" : null,
      "BLPU_STATE_CODE_DESCRIPTION" : "Unknown/Not applicable",
      "TOPOGRAPHY_LAYER_TOID" : "osgb1000034933439",
      "PARENT_UPRN" : "38209195",
      "LAST_UPDATE_DATE" : "12/11/2018",
      "ENTRY_DATE" : "07/07/1997",
      "LANGUAGE" : "EN",
      "MATCH" : 1.0,
      "MATCH_DESCRIPTION" : "EXACT"
    }
  }, {
    "DPA" : {
      "UPRN" : "38209201",
      "UDPRN" : "12489025",
      "ADDRESS" : "15, CONCERT SQUARE APARTMENTS, 29, FLEET STREET, LIVERPOOL, L1 4AR",
      "SUB_BUILDING_NAME" : "15",
      "BUILDING_NAME" : "CONCERT SQUARE APARTMENTS",
      "BUILDING_NUMBER" : "29",
      "THOROUGHFARE_NAME" : "FLEET STREET",
      "POST_TOWN" : "LIVERPOOL",
      "POSTCODE" : "L1 4AR",
      "RPC" : "2",
      "X_COORDINATE" : 334893.0,
      "Y_COORDINATE" : 390069.0,
      "STATUS" : "APPROVED",
      "LOGICAL_STATUS_CODE" : "1",
      "CLASSIFICATION_CODE" : "RD06",
      "CLASSIFICATION_CODE_DESCRIPTION" : "Self Contained Flat (Includes Maisonette / Apartment)",
      "LOCAL_CUSTODIAN_CODE" : 4310,
      "LOCAL_CUSTODIAN_CODE_DESCRIPTION" : "LIVERPOOL",
      "POSTAL_ADDRESS_CODE" : "D",
      "POSTAL_ADDRESS_CODE_DESCRIPTION" : "A record which is linked to PAF",
      "BLPU_STATE_CODE" : null,
      "BLPU_STATE_CODE_DESCRIPTION" : "Unknown/Not applicable",
      "TOPOGRAPHY_LAYER_TOID" : "osgb1000034933439",
      "PARENT_UPRN" : "38209195",
      "LAST_UPDATE_DATE" : "12/11/2018",
      "ENTRY_DATE" : "07/07/1997",
      "LANGUAGE" : "EN",
      "MATCH" : 1.0,
      "MATCH_DESCRIPTION" : "EXACT"
    }
  }, {
    "DPA" : {
      "UPRN" : "38209202",
      "UDPRN" : "12489026",
      "ADDRESS" : "16, CONCERT SQUARE APARTMENTS, 29, FLEET STREET, LIVERPOOL, L1 4AR",
      "SUB_BUILDING_NAME" : "16",
      "BUILDING_NAME" : "CONCERT SQUARE APARTMENTS",
      "BUILDING_NUMBER" : "29",
      "THOROUGHFARE_NAME" : "FLEET STREET",
      "POST_TOWN" : "LIVERPOOL",
      "POSTCODE" : "L1 4AR",
      "RPC" : "2",
      "X_COORDINATE" : 334893.0,
      "Y_COORDINATE" : 390069.0,
      "STATUS" : "APPROVED",
      "LOGICAL_STATUS_CODE" : "1",
      "CLASSIFICATION_CODE" : "RD06",
      "CLASSIFICATION_CODE_DESCRIPTION" : "Self Contained Flat (Includes Maisonette / Apartment)",
      "LOCAL_CUSTODIAN_CODE" : 4310,
      "LOCAL_CUSTODIAN_CODE_DESCRIPTION" : "LIVERPOOL",
      "POSTAL_ADDRESS_CODE" : "D",
      "POSTAL_ADDRESS_CODE_DESCRIPTION" : "A record which is linked to PAF",
      "BLPU_STATE_CODE" : null,
      "BLPU_STATE_CODE_DESCRIPTION" : "Unknown/Not applicable",
      "TOPOGRAPHY_LAYER_TOID" : "osgb1000034933439",
      "PARENT_UPRN" : "38209195",
      "LAST_UPDATE_DATE" : "12/11/2018",
      "ENTRY_DATE" : "07/07/1997",
      "LANGUAGE" : "EN",
      "MATCH" : 1.0,
      "MATCH_DESCRIPTION" : "EXACT"
    }
  }, {
    "DPA" : {
      "UPRN" : "38209203",
      "UDPRN" : "12489027",
      "ADDRESS" : "17, CONCERT SQUARE APARTMENTS, 29, FLEET STREET, LIVERPOOL, L1 4AR",
      "SUB_BUILDING_NAME" : "17",
      "BUILDING_NAME" : "CONCERT SQUARE APARTMENTS",
      "BUILDING_NUMBER" : "29",
      "THOROUGHFARE_NAME" : "FLEET STREET",
      "POST_TOWN" : "LIVERPOOL",
      "POSTCODE" : "L1 4AR",
      "RPC" : "2",
      "X_COORDINATE" : 334893.0,
      "Y_COORDINATE" : 390069.0,
      "STATUS" : "APPROVED",
      "LOGICAL_STATUS_CODE" : "1",
      "CLASSIFICATION_CODE" : "RD06",
      "CLASSIFICATION_CODE_DESCRIPTION" : "Self Contained Flat (Includes Maisonette / Apartment)",
      "LOCAL_CUSTODIAN_CODE" : 4310,
      "LOCAL_CUSTODIAN_CODE_DESCRIPTION" : "LIVERPOOL",
      "POSTAL_ADDRESS_CODE" : "D",
      "POSTAL_ADDRESS_CODE_DESCRIPTION" : "A record which is linked to PAF",
      "BLPU_STATE_CODE" : null,
      "BLPU_STATE_CODE_DESCRIPTION" : "Unknown/Not applicable",
      "TOPOGRAPHY_LAYER_TOID" : "osgb1000034933439",
      "PARENT_UPRN" : "38209195",
      "LAST_UPDATE_DATE" : "12/11/2018",
      "ENTRY_DATE" : "07/07/1997",
      "LANGUAGE" : "EN",
      "MATCH" : 1.0,
      "MATCH_DESCRIPTION" : "EXACT"
    }
  }, {
    "DPA" : {
      "UPRN" : "38209204",
      "UDPRN" : "12489028",
      "ADDRESS" : "18, CONCERT SQUARE APARTMENTS, 29, FLEET STREET, LIVERPOOL, L1 4AR",
      "SUB_BUILDING_NAME" : "18",
      "BUILDING_NAME" : "CONCERT SQUARE APARTMENTS",
      "BUILDING_NUMBER" : "29",
      "THOROUGHFARE_NAME" : "FLEET STREET",
      "POST_TOWN" : "LIVERPOOL",
      "POSTCODE" : "L1 4AR",
      "RPC" : "2",
      "X_COORDINATE" : 334893.0,
      "Y_COORDINATE" : 390069.0,
      "STATUS" : "APPROVED",
      "LOGICAL_STATUS_CODE" : "1",
      "CLASSIFICATION_CODE" : "RD06",
      "CLASSIFICATION_CODE_DESCRIPTION" : "Self Contained Flat (Includes Maisonette / Apartment)",
      "LOCAL_CUSTODIAN_CODE" : 4310,
      "LOCAL_CUSTODIAN_CODE_DESCRIPTION" : "LIVERPOOL",
      "POSTAL_ADDRESS_CODE" : "D",
      "POSTAL_ADDRESS_CODE_DESCRIPTION" : "A record which is linked to PAF",
      "BLPU_STATE_CODE" : null,
      "BLPU_STATE_CODE_DESCRIPTION" : "Unknown/Not applicable",
      "TOPOGRAPHY_LAYER_TOID" : "osgb1000034933439",
      "PARENT_UPRN" : "38209195",
      "LAST_UPDATE_DATE" : "12/11/2018",
      "ENTRY_DATE" : "07/07/1997",
      "LANGUAGE" : "EN",
      "MATCH" : 1.0,
      "MATCH_DESCRIPTION" : "EXACT"
    }
  }, {
    "DPA" : {
      "UPRN" : "38283121",
      "UDPRN" : "28018124",
      "ADDRESS" : "UNIT 100, VANILLA FACTORY, 39, FLEET STREET, LIVERPOOL, L1 4AR",
      "SUB_BUILDING_NAME" : "UNIT 100",
      "BUILDING_NAME" : "VANILLA FACTORY",
      "BUILDING_NUMBER" : "39",
      "THOROUGHFARE_NAME" : "FLEET STREET",
      "POST_TOWN" : "LIVERPOOL",
      "POSTCODE" : "L1 4AR",
      "RPC" : "2",
      "X_COORDINATE" : 334958.0,
      "Y_COORDINATE" : 390015.0,
      "STATUS" : "APPROVED",
      "LOGICAL_STATUS_CODE" : "1",
      "CLASSIFICATION_CODE" : "CO01",
      "CLASSIFICATION_CODE_DESCRIPTION" : "Office / Work Studio",
      "LOCAL_CUSTODIAN_CODE" : 4310,
      "LOCAL_CUSTODIAN_CODE_DESCRIPTION" : "LIVERPOOL",
      "POSTAL_ADDRESS_CODE" : "D",
      "POSTAL_ADDRESS_CODE_DESCRIPTION" : "A record which is linked to PAF",
      "BLPU_STATE_CODE" : null,
      "BLPU_STATE_CODE_DESCRIPTION" : "Unknown/Not applicable",
      "TOPOGRAPHY_LAYER_TOID" : "osgb1000034933459",
      "PARENT_UPRN" : "38057465",
      "LAST_UPDATE_DATE" : "19/04/2019",
      "ENTRY_DATE" : "13/07/2009",
      "LANGUAGE" : "EN",
      "MATCH" : 1.0,
      "MATCH_DESCRIPTION" : "EXACT"
    }
  }, {
    "DPA" : {
      "UPRN" : "38283095",
      "UDPRN" : "51755019",
      "ADDRESS" : "UNIT 201, VANILLA FACTORY, 39, FLEET STREET, LIVERPOOL, L1 4AR",
      "SUB_BUILDING_NAME" : "UNIT 201",
      "BUILDING_NAME" : "VANILLA FACTORY",
      "BUILDING_NUMBER" : "39",
      "THOROUGHFARE_NAME" : "FLEET STREET",
      "POST_TOWN" : "LIVERPOOL",
      "POSTCODE" : "L1 4AR",
      "RPC" : "2",
      "X_COORDINATE" : 334958.0,
      "Y_COORDINATE" : 390015.0,
      "STATUS" : "APPROVED",
      "LOGICAL_STATUS_CODE" : "1",
      "CLASSIFICATION_CODE" : "CR08",
      "CLASSIFICATION_CODE_DESCRIPTION" : "Shop / Showroom",
      "LOCAL_CUSTODIAN_CODE" : 4310,
      "LOCAL_CUSTODIAN_CODE_DESCRIPTION" : "LIVERPOOL",
      "POSTAL_ADDRESS_CODE" : "D",
      "POSTAL_ADDRESS_CODE_DESCRIPTION" : "A record which is linked to PAF",
      "BLPU_STATE_CODE" : null,
      "BLPU_STATE_CODE_DESCRIPTION" : "Unknown/Not applicable",
      "TOPOGRAPHY_LAYER_TOID" : "osgb1000034933459",
      "PARENT_UPRN" : "38057465",
      "LAST_UPDATE_DATE" : "10/02/2016",
      "ENTRY_DATE" : "13/07/2009",
      "LANGUAGE" : "EN",
      "MATCH" : 1.0,
      "MATCH_DESCRIPTION" : "EXACT"
    }
  }, {
    "DPA" : {
      "UPRN" : "38283096",
      "UDPRN" : "28643772",
      "ADDRESS" : "SMILING WOLF, UNIT 202, VANILLA FACTORY, 39, FLEET STREET, LIVERPOOL, L1 4AR",
      "ORGANISATION_NAME" : "SMILING WOLF",
      "SUB_BUILDING_NAME" : "UNIT 202",
      "BUILDING_NAME" : "VANILLA FACTORY",
      "BUILDING_NUMBER" : "39",
      "THOROUGHFARE_NAME" : "FLEET STREET",
      "POST_TOWN" : "LIVERPOOL",
      "POSTCODE" : "L1 4AR",
      "RPC" : "2",
      "X_COORDINATE" : 334958.0,
      "Y_COORDINATE" : 390015.0,
      "STATUS" : "APPROVED",
      "LOGICAL_STATUS_CODE" : "1",
      "CLASSIFICATION_CODE" : "CR08",
      "CLASSIFICATION_CODE_DESCRIPTION" : "Shop / Showroom",
      "LOCAL_CUSTODIAN_CODE" : 4310,
      "LOCAL_CUSTODIAN_CODE_DESCRIPTION" : "LIVERPOOL",
      "POSTAL_ADDRESS_CODE" : "D",
      "POSTAL_ADDRESS_CODE_DESCRIPTION" : "A record which is linked to PAF",
      "BLPU_STATE_CODE" : null,
      "BLPU_STATE_CODE_DESCRIPTION" : "Unknown/Not applicable",
      "TOPOGRAPHY_LAYER_TOID" : "osgb1000034933459",
      "PARENT_UPRN" : "38057465",
      "LAST_UPDATE_DATE" : "10/02/2016",
      "ENTRY_DATE" : "13/07/2009",
      "LANGUAGE" : "EN",
      "MATCH" : 1.0,
      "MATCH_DESCRIPTION" : "EXACT"
    }
  }, {
    "DPA" : {
      "UPRN" : "38283097",
      "UDPRN" : "51636859",
      "ADDRESS" : "UNIT 203, VANILLA FACTORY, 39, FLEET STREET, LIVERPOOL, L1 4AR",
      "SUB_BUILDING_NAME" : "UNIT 203",
      "BUILDING_NAME" : "VANILLA FACTORY",
      "BUILDING_NUMBER" : "39",
      "THOROUGHFARE_NAME" : "FLEET STREET",
      "POST_TOWN" : "LIVERPOOL",
      "POSTCODE" : "L1 4AR",
      "RPC" : "2",
      "X_COORDINATE" : 334958.0,
      "Y_COORDINATE" : 390015.0,
      "STATUS" : "APPROVED",
      "LOGICAL_STATUS_CODE" : "1",
      "CLASSIFICATION_CODE" : "CR07",
      "CLASSIFICATION_CODE_DESCRIPTION" : "Restaurant / Cafeteria",
      "LOCAL_CUSTODIAN_CODE" : 4310,
      "LOCAL_CUSTODIAN_CODE_DESCRIPTION" : "LIVERPOOL",
      "POSTAL_ADDRESS_CODE" : "D",
      "POSTAL_ADDRESS_CODE_DESCRIPTION" : "A record which is linked to PAF",
      "BLPU_STATE_CODE" : null,
      "BLPU_STATE_CODE_DESCRIPTION" : "Unknown/Not applicable",
      "TOPOGRAPHY_LAYER_TOID" : "osgb1000034933459",
      "PARENT_UPRN" : "38057465",
      "LAST_UPDATE_DATE" : "10/02/2016",
      "ENTRY_DATE" : "13/07/2009",
      "LANGUAGE" : "EN",
      "MATCH" : 1.0,
      "MATCH_DESCRIPTION" : "EXACT"
    }
  }, {
    "DPA" : {
      "UPRN" : "38283098",
      "UDPRN" : "27683459",
      "ADDRESS" : "URBAN SPLASH GROUP LTD, UNIT 204, VANILLA FACTORY, 39, FLEET STREET, LIVERPOOL, L1 4AR",
      "ORGANISATION_NAME" : "URBAN SPLASH GROUP LTD",
      "SUB_BUILDING_NAME" : "UNIT 204",
      "BUILDING_NAME" : "VANILLA FACTORY",
      "BUILDING_NUMBER" : "39",
      "THOROUGHFARE_NAME" : "FLEET STREET",
      "POST_TOWN" : "LIVERPOOL",
      "POSTCODE" : "L1 4AR",
      "RPC" : "2",
      "X_COORDINATE" : 334958.0,
      "Y_COORDINATE" : 390015.0,
      "STATUS" : "APPROVED",
      "LOGICAL_STATUS_CODE" : "1",
      "CLASSIFICATION_CODE" : "CR08",
      "CLASSIFICATION_CODE_DESCRIPTION" : "Shop / Showroom",
      "LOCAL_CUSTODIAN_CODE" : 4310,
      "LOCAL_CUSTODIAN_CODE_DESCRIPTION" : "LIVERPOOL",
      "POSTAL_ADDRESS_CODE" : "D",
      "POSTAL_ADDRESS_CODE_DESCRIPTION" : "A record which is linked to PAF",
      "BLPU_STATE_CODE" : null,
      "BLPU_STATE_CODE_DESCRIPTION" : "Unknown/Not applicable",
      "TOPOGRAPHY_LAYER_TOID" : "osgb1000034933459",
      "PARENT_UPRN" : "38057465",
      "LAST_UPDATE_DATE" : "10/02/2016",
      "ENTRY_DATE" : "13/07/2009",
      "LANGUAGE" : "EN",
      "MATCH" : 1.0,
      "MATCH_DESCRIPTION" : "EXACT"
    }
  }, {
    "DPA" : {
      "UPRN" : "38283102",
      "UDPRN" : "51755027",
      "ADDRESS" : "UNIT 206-208, VANILLA FACTORY, 39, FLEET STREET, LIVERPOOL, L1 4AR",
      "SUB_BUILDING_NAME" : "UNIT 206-208",
      "BUILDING_NAME" : "VANILLA FACTORY",
      "BUILDING_NUMBER" : "39",
      "THOROUGHFARE_NAME" : "FLEET STREET",
      "POST_TOWN" : "LIVERPOOL",
      "POSTCODE" : "L1 4AR",
      "RPC" : "2",
      "X_COORDINATE" : 334958.0,
      "Y_COORDINATE" : 390015.0,
      "STATUS" : "APPROVED",
      "LOGICAL_STATUS_CODE" : "1",
      "CLASSIFICATION_CODE" : "CR08",
      "CLASSIFICATION_CODE_DESCRIPTION" : "Shop / Showroom",
      "LOCAL_CUSTODIAN_CODE" : 4310,
      "LOCAL_CUSTODIAN_CODE_DESCRIPTION" : "LIVERPOOL",
      "POSTAL_ADDRESS_CODE" : "D",
      "POSTAL_ADDRESS_CODE_DESCRIPTION" : "A record which is linked to PAF",
      "BLPU_STATE_CODE" : null,
      "BLPU_STATE_CODE_DESCRIPTION" : "Unknown/Not applicable",
      "TOPOGRAPHY_LAYER_TOID" : "osgb1000034933459",
      "PARENT_UPRN" : "38057465",
      "LAST_UPDATE_DATE" : "10/02/2016",
      "ENTRY_DATE" : "13/07/2009",
      "LANGUAGE" : "EN",
      "MATCH" : 1.0,
      "MATCH_DESCRIPTION" : "EXACT"
    }
  }, {
    "DPA" : {
      "UPRN" : "38283101",
      "UDPRN" : "28642394",
      "ADDRESS" : "ELLIS WILLIAMS ARCHITECTS, UNIT 207, VANILLA FACTORY, 39, FLEET STREET, LIVERPOOL, L1 4AR",
      "ORGANISATION_NAME" : "ELLIS WILLIAMS ARCHITECTS",
      "SUB_BUILDING_NAME" : "UNIT 207",
      "BUILDING_NAME" : "VANILLA FACTORY",
      "BUILDING_NUMBER" : "39",
      "THOROUGHFARE_NAME" : "FLEET STREET",
      "POST_TOWN" : "LIVERPOOL",
      "POSTCODE" : "L1 4AR",
      "RPC" : "2",
      "X_COORDINATE" : 334958.0,
      "Y_COORDINATE" : 390015.0,
      "STATUS" : "APPROVED",
      "LOGICAL_STATUS_CODE" : "1",
      "CLASSIFICATION_CODE" : "CR08",
      "CLASSIFICATION_CODE_DESCRIPTION" : "Shop / Showroom",
      "LOCAL_CUSTODIAN_CODE" : 4310,
      "LOCAL_CUSTODIAN_CODE_DESCRIPTION" : "LIVERPOOL",
      "POSTAL_ADDRESS_CODE" : "D",
      "POSTAL_ADDRESS_CODE_DESCRIPTION" : "A record which is linked to PAF",
      "BLPU_STATE_CODE" : null,
      "BLPU_STATE_CODE_DESCRIPTION" : "Unknown/Not applicable",
      "TOPOGRAPHY_LAYER_TOID" : "osgb1000034933459",
      "PARENT_UPRN" : "38057465",
      "LAST_UPDATE_DATE" : "10/02/2016",
      "ENTRY_DATE" : "13/07/2009",
      "LANGUAGE" : "EN",
      "MATCH" : 1.0,
      "MATCH_DESCRIPTION" : "EXACT"
    }
  }, {
    "DPA" : {
      "UPRN" : "38283103",
      "UDPRN" : "51755038",
      "ADDRESS" : "UNIT 209, VANILLA FACTORY, 39, FLEET STREET, LIVERPOOL, L1 4AR",
      "SUB_BUILDING_NAME" : "UNIT 209",
      "BUILDING_NAME" : "VANILLA FACTORY",
      "BUILDING_NUMBER" : "39",
      "THOROUGHFARE_NAME" : "FLEET STREET",
      "POST_TOWN" : "LIVERPOOL",
      "POSTCODE" : "L1 4AR",
      "RPC" : "2",
      "X_COORDINATE" : 334958.0,
      "Y_COORDINATE" : 390015.0,
      "STATUS" : "APPROVED",
      "LOGICAL_STATUS_CODE" : "1",
      "CLASSIFICATION_CODE" : "CR08",
      "CLASSIFICATION_CODE_DESCRIPTION" : "Shop / Showroom",
      "LOCAL_CUSTODIAN_CODE" : 4310,
      "LOCAL_CUSTODIAN_CODE_DESCRIPTION" : "LIVERPOOL",
      "POSTAL_ADDRESS_CODE" : "D",
      "POSTAL_ADDRESS_CODE_DESCRIPTION" : "A record which is linked to PAF",
      "BLPU_STATE_CODE" : null,
      "BLPU_STATE_CODE_DESCRIPTION" : "Unknown/Not applicable",
      "TOPOGRAPHY_LAYER_TOID" : "osgb1000034933459",
      "PARENT_UPRN" : "38057465",
      "LAST_UPDATE_DATE" : "10/02/2016",
      "ENTRY_DATE" : "13/07/2009",
      "LANGUAGE" : "EN",
      "MATCH" : 1.0,
      "MATCH_DESCRIPTION" : "EXACT"
    }
  }, {
    "DPA" : {
      "UPRN" : "38283104",
      "UDPRN" : "51755037",
      "ADDRESS" : "J D A ARCHITECTS, UNIT 210, VANILLA FACTORY, 39, FLEET STREET, LIVERPOOL, L1 4AR",
      "ORGANISATION_NAME" : "J D A ARCHITECTS",
      "SUB_BUILDING_NAME" : "UNIT 210",
      "BUILDING_NAME" : "VANILLA FACTORY",
      "BUILDING_NUMBER" : "39",
      "THOROUGHFARE_NAME" : "FLEET STREET",
      "POST_TOWN" : "LIVERPOOL",
      "POSTCODE" : "L1 4AR",
      "RPC" : "2",
      "X_COORDINATE" : 334958.0,
      "Y_COORDINATE" : 390015.0,
      "STATUS" : "APPROVED",
      "LOGICAL_STATUS_CODE" : "1",
      "CLASSIFICATION_CODE" : "CR08",
      "CLASSIFICATION_CODE_DESCRIPTION" : "Shop / Showroom",
      "LOCAL_CUSTODIAN_CODE" : 4310,
      "LOCAL_CUSTODIAN_CODE_DESCRIPTION" : "LIVERPOOL",
      "POSTAL_ADDRESS_CODE" : "D",
      "POSTAL_ADDRESS_CODE_DESCRIPTION" : "A record which is linked to PAF",
      "BLPU_STATE_CODE" : null,
      "BLPU_STATE_CODE_DESCRIPTION" : "Unknown/Not applicable",
      "TOPOGRAPHY_LAYER_TOID" : "osgb1000034933459",
      "PARENT_UPRN" : "38057465",
      "LAST_UPDATE_DATE" : "10/02/2016",
      "ENTRY_DATE" : "13/07/2009",
      "LANGUAGE" : "EN",
      "MATCH" : 1.0,
      "MATCH_DESCRIPTION" : "EXACT"
    }
  }, {
    "DPA" : {
      "UPRN" : "38283105",
      "UDPRN" : "28045656",
      "ADDRESS" : "UNIT 211, VANILLA FACTORY, 39, FLEET STREET, LIVERPOOL, L1 4AR",
      "SUB_BUILDING_NAME" : "UNIT 211",
      "BUILDING_NAME" : "VANILLA FACTORY",
      "BUILDING_NUMBER" : "39",
      "THOROUGHFARE_NAME" : "FLEET STREET",
      "POST_TOWN" : "LIVERPOOL",
      "POSTCODE" : "L1 4AR",
      "RPC" : "2",
      "X_COORDINATE" : 334958.0,
      "Y_COORDINATE" : 390015.0,
      "STATUS" : "APPROVED",
      "LOGICAL_STATUS_CODE" : "1",
      "CLASSIFICATION_CODE" : "CR08",
      "CLASSIFICATION_CODE_DESCRIPTION" : "Shop / Showroom",
      "LOCAL_CUSTODIAN_CODE" : 4310,
      "LOCAL_CUSTODIAN_CODE_DESCRIPTION" : "LIVERPOOL",
      "POSTAL_ADDRESS_CODE" : "D",
      "POSTAL_ADDRESS_CODE_DESCRIPTION" : "A record which is linked to PAF",
      "BLPU_STATE_CODE" : null,
      "BLPU_STATE_CODE_DESCRIPTION" : "Unknown/Not applicable",
      "TOPOGRAPHY_LAYER_TOID" : "osgb1000034933459",
      "PARENT_UPRN" : "38057465",
      "LAST_UPDATE_DATE" : "10/02/2016",
      "ENTRY_DATE" : "13/07/2009",
      "LANGUAGE" : "EN",
      "MATCH" : 1.0,
      "MATCH_DESCRIPTION" : "EXACT"
    }
  }, {
    "DPA" : {
      "UPRN" : "38283106",
      "UDPRN" : "51755039",
      "ADDRESS" : "UNIT 212, VANILLA FACTORY, 39, FLEET STREET, LIVERPOOL, L1 4AR",
      "SUB_BUILDING_NAME" : "UNIT 212",
      "BUILDING_NAME" : "VANILLA FACTORY",
      "BUILDING_NUMBER" : "39",
      "THOROUGHFARE_NAME" : "FLEET STREET",
      "POST_TOWN" : "LIVERPOOL",
      "POSTCODE" : "L1 4AR",
      "RPC" : "2",
      "X_COORDINATE" : 334958.0,
      "Y_COORDINATE" : 390015.0,
      "STATUS" : "APPROVED",
      "LOGICAL_STATUS_CODE" : "1",
      "CLASSIFICATION_CODE" : "CR",
      "CLASSIFICATION_CODE_DESCRIPTION" : "Retail",
      "LOCAL_CUSTODIAN_CODE" : 4310,
      "LOCAL_CUSTODIAN_CODE_DESCRIPTION" : "LIVERPOOL",
      "POSTAL_ADDRESS_CODE" : "D",
      "POSTAL_ADDRESS_CODE_DESCRIPTION" : "A record which is linked to PAF",
      "BLPU_STATE_CODE" : null,
      "BLPU_STATE_CODE_DESCRIPTION" : "Unknown/Not applicable",
      "TOPOGRAPHY_LAYER_TOID" : "osgb1000034933459",
      "PARENT_UPRN" : "38057465",
      "LAST_UPDATE_DATE" : "10/02/2016",
      "ENTRY_DATE" : "13/07/2009",
      "LANGUAGE" : "EN",
      "MATCH" : 1.0,
      "MATCH_DESCRIPTION" : "EXACT"
    }
  }, {
    "DPA" : {
      "UPRN" : "38283107",
      "UDPRN" : "28365319",
      "ADDRESS" : "ANDREW COLLINGE, UNIT 213, VANILLA FACTORY, 39, FLEET STREET, LIVERPOOL, L1 4AR",
      "ORGANISATION_NAME" : "ANDREW COLLINGE",
      "SUB_BUILDING_NAME" : "UNIT 213",
      "BUILDING_NAME" : "VANILLA FACTORY",
      "BUILDING_NUMBER" : "39",
      "THOROUGHFARE_NAME" : "FLEET STREET",
      "POST_TOWN" : "LIVERPOOL",
      "POSTCODE" : "L1 4AR",
      "RPC" : "2",
      "X_COORDINATE" : 334958.0,
      "Y_COORDINATE" : 390015.0,
      "STATUS" : "APPROVED",
      "LOGICAL_STATUS_CODE" : "1",
      "CLASSIFICATION_CODE" : "CR08",
      "CLASSIFICATION_CODE_DESCRIPTION" : "Shop / Showroom",
      "LOCAL_CUSTODIAN_CODE" : 4310,
      "LOCAL_CUSTODIAN_CODE_DESCRIPTION" : "LIVERPOOL",
      "POSTAL_ADDRESS_CODE" : "D",
      "POSTAL_ADDRESS_CODE_DESCRIPTION" : "A record which is linked to PAF",
      "BLPU_STATE_CODE" : null,
      "BLPU_STATE_CODE_DESCRIPTION" : "Unknown/Not applicable",
      "TOPOGRAPHY_LAYER_TOID" : "osgb1000034933459",
      "PARENT_UPRN" : "38057465",
      "LAST_UPDATE_DATE" : "10/02/2016",
      "ENTRY_DATE" : "13/07/2009",
      "LANGUAGE" : "EN",
      "MATCH" : 1.0,
      "MATCH_DESCRIPTION" : "EXACT"
    }
  }, {
    "DPA" : {
      "UPRN" : "38292401",
      "UDPRN" : "51755035",
      "ADDRESS" : "UNIT 300, VANILLA FACTORY, 39, FLEET STREET, LIVERPOOL, L1 4AR",
      "SUB_BUILDING_NAME" : "UNIT 300",
      "BUILDING_NAME" : "VANILLA FACTORY",
      "BUILDING_NUMBER" : "39",
      "THOROUGHFARE_NAME" : "FLEET STREET",
      "POST_TOWN" : "LIVERPOOL",
      "POSTCODE" : "L1 4AR",
      "RPC" : "2",
      "X_COORDINATE" : 334958.0,
      "Y_COORDINATE" : 390015.0,
      "STATUS" : "APPROVED",
      "LOGICAL_STATUS_CODE" : "1",
      "CLASSIFICATION_CODE" : "CO01",
      "CLASSIFICATION_CODE_DESCRIPTION" : "Office / Work Studio",
      "LOCAL_CUSTODIAN_CODE" : 4310,
      "LOCAL_CUSTODIAN_CODE_DESCRIPTION" : "LIVERPOOL",
      "POSTAL_ADDRESS_CODE" : "D",
      "POSTAL_ADDRESS_CODE_DESCRIPTION" : "A record which is linked to PAF",
      "BLPU_STATE_CODE" : null,
      "BLPU_STATE_CODE_DESCRIPTION" : "Unknown/Not applicable",
      "TOPOGRAPHY_LAYER_TOID" : "osgb1000034933459",
      "PARENT_UPRN" : "38057465",
      "LAST_UPDATE_DATE" : "10/02/2016",
      "ENTRY_DATE" : "20/07/2011",
      "LANGUAGE" : "EN",
      "MATCH" : 1.0,
      "MATCH_DESCRIPTION" : "EXACT"
    }
  }, {
    "DPA" : {
      "UPRN" : "10091900403",
      "UDPRN" : "54166448",
      "ADDRESS" : "URBAN SPLASH WORK LTD, UNIT 301, VANILLA FACTORY, 39, FLEET STREET, LIVERPOOL, L1 4AR",
      "ORGANISATION_NAME" : "URBAN SPLASH WORK LTD",
      "SUB_BUILDING_NAME" : "UNIT 301",
      "BUILDING_NAME" : "VANILLA FACTORY",
      "BUILDING_NUMBER" : "39",
      "THOROUGHFARE_NAME" : "FLEET STREET",
      "POST_TOWN" : "LIVERPOOL",
      "POSTCODE" : "L1 4AR",
      "RPC" : "2",
      "X_COORDINATE" : 334958.0,
      "Y_COORDINATE" : 390015.0,
      "STATUS" : "APPROVED",
      "LOGICAL_STATUS_CODE" : "1",
      "CLASSIFICATION_CODE" : "OR04",
      "CLASSIFICATION_CODE_DESCRIPTION" : "Additional Mail / Packet Addressee",
      "LOCAL_CUSTODIAN_CODE" : 7655,
      "LOCAL_CUSTODIAN_CODE_DESCRIPTION" : "ORDNANCE SURVEY",
      "POSTAL_ADDRESS_CODE" : "D",
      "POSTAL_ADDRESS_CODE_DESCRIPTION" : "A record which is linked to PAF",
      "BLPU_STATE_CODE" : null,
      "BLPU_STATE_CODE_DESCRIPTION" : "Unknown/Not applicable",
      "TOPOGRAPHY_LAYER_TOID" : "osgb1000034933459",
      "PARENT_UPRN" : "38292401",
      "LAST_UPDATE_DATE" : "06/02/2016",
      "ENTRY_DATE" : "18/01/2016",
      "LANGUAGE" : "EN",
      "MATCH" : 1.0,
      "MATCH_DESCRIPTION" : "EXACT"
    }
  }, {
    "DPA" : {
      "UPRN" : "38283111",
      "UDPRN" : "28020796",
      "ADDRESS" : "UNIT 302, VANILLA FACTORY, 39, FLEET STREET, LIVERPOOL, L1 4AR",
      "SUB_BUILDING_NAME" : "UNIT 302",
      "BUILDING_NAME" : "VANILLA FACTORY",
      "BUILDING_NUMBER" : "39",
      "THOROUGHFARE_NAME" : "FLEET STREET",
      "POST_TOWN" : "LIVERPOOL",
      "POSTCODE" : "L1 4AR",
      "RPC" : "2",
      "X_COORDINATE" : 334958.0,
      "Y_COORDINATE" : 390015.0,
      "STATUS" : "APPROVED",
      "LOGICAL_STATUS_CODE" : "1",
      "CLASSIFICATION_CODE" : "CO01",
      "CLASSIFICATION_CODE_DESCRIPTION" : "Office / Work Studio",
      "LOCAL_CUSTODIAN_CODE" : 4310,
      "LOCAL_CUSTODIAN_CODE_DESCRIPTION" : "LIVERPOOL",
      "POSTAL_ADDRESS_CODE" : "D",
      "POSTAL_ADDRESS_CODE_DESCRIPTION" : "A record which is linked to PAF",
      "BLPU_STATE_CODE" : null,
      "BLPU_STATE_CODE_DESCRIPTION" : "Unknown/Not applicable",
      "TOPOGRAPHY_LAYER_TOID" : "osgb1000034933459",
      "PARENT_UPRN" : "38057465",
      "LAST_UPDATE_DATE" : "10/02/2016",
      "ENTRY_DATE" : "13/07/2009",
      "LANGUAGE" : "EN",
      "MATCH" : 1.0,
      "MATCH_DESCRIPTION" : "EXACT"
    }
  }, {
    "DPA" : {
      "UPRN" : "38283112",
      "UDPRN" : "54214936",
      "ADDRESS" : "THERESA GRIFFIN MEP, UNIT 303, VANILLA FACTORY, 39, FLEET STREET, LIVERPOOL, L1 4AR",
      "ORGANISATION_NAME" : "THERESA GRIFFIN MEP",
      "SUB_BUILDING_NAME" : "UNIT 303",
      "BUILDING_NAME" : "VANILLA FACTORY",
      "BUILDING_NUMBER" : "39",
      "THOROUGHFARE_NAME" : "FLEET STREET",
      "POST_TOWN" : "LIVERPOOL",
      "POSTCODE" : "L1 4AR",
      "RPC" : "2",
      "X_COORDINATE" : 334958.0,
      "Y_COORDINATE" : 390015.0,
      "STATUS" : "APPROVED",
      "LOGICAL_STATUS_CODE" : "1",
      "CLASSIFICATION_CODE" : "C",
      "CLASSIFICATION_CODE_DESCRIPTION" : "Commercial",
      "LOCAL_CUSTODIAN_CODE" : 4310,
      "LOCAL_CUSTODIAN_CODE_DESCRIPTION" : "LIVERPOOL",
      "POSTAL_ADDRESS_CODE" : "D",
      "POSTAL_ADDRESS_CODE_DESCRIPTION" : "A record which is linked to PAF",
      "BLPU_STATE_CODE" : null,
      "BLPU_STATE_CODE_DESCRIPTION" : "Unknown/Not applicable",
      "TOPOGRAPHY_LAYER_TOID" : "osgb1000034933459",
      "PARENT_UPRN" : "38057465",
      "LAST_UPDATE_DATE" : "21/03/2016",
      "ENTRY_DATE" : "13/07/2009",
      "LANGUAGE" : "EN",
      "MATCH" : 1.0,
      "MATCH_DESCRIPTION" : "EXACT"
    }
  }, {
    "DPA" : {
      "UPRN" : "38283113",
      "UDPRN" : "51498648",
      "ADDRESS" : "BLADON & KIRKHAM, UNIT 304, VANILLA FACTORY, 39, FLEET STREET, LIVERPOOL, L1 4AR",
      "ORGANISATION_NAME" : "BLADON & KIRKHAM",
      "SUB_BUILDING_NAME" : "UNIT 304",
      "BUILDING_NAME" : "VANILLA FACTORY",
      "BUILDING_NUMBER" : "39",
      "THOROUGHFARE_NAME" : "FLEET STREET",
      "POST_TOWN" : "LIVERPOOL",
      "POSTCODE" : "L1 4AR",
      "RPC" : "2",
      "X_COORDINATE" : 334958.0,
      "Y_COORDINATE" : 390015.0,
      "STATUS" : "APPROVED",
      "LOGICAL_STATUS_CODE" : "1",
      "CLASSIFICATION_CODE" : "C",
      "CLASSIFICATION_CODE_DESCRIPTION" : "Commercial",
      "LOCAL_CUSTODIAN_CODE" : 4310,
      "LOCAL_CUSTODIAN_CODE_DESCRIPTION" : "LIVERPOOL",
      "POSTAL_ADDRESS_CODE" : "D",
      "POSTAL_ADDRESS_CODE_DESCRIPTION" : "A record which is linked to PAF",
      "BLPU_STATE_CODE" : null,
      "BLPU_STATE_CODE_DESCRIPTION" : "Unknown/Not applicable",
      "TOPOGRAPHY_LAYER_TOID" : "osgb1000034933459",
      "PARENT_UPRN" : "38057465",
      "LAST_UPDATE_DATE" : "10/02/2016",
      "ENTRY_DATE" : "13/07/2009",
      "LANGUAGE" : "EN",
      "MATCH" : 1.0,
      "MATCH_DESCRIPTION" : "EXACT"
    }
  }, {
    "DPA" : {
      "UPRN" : "38283114",
      "UDPRN" : "51764040",
      "ADDRESS" : "MODULARIZE LTD, UNIT 305, VANILLA FACTORY, 39, FLEET STREET, LIVERPOOL, L1 4AR",
      "ORGANISATION_NAME" : "MODULARIZE LTD",
      "SUB_BUILDING_NAME" : "UNIT 305",
      "BUILDING_NAME" : "VANILLA FACTORY",
      "BUILDING_NUMBER" : "39",
      "THOROUGHFARE_NAME" : "FLEET STREET",
      "POST_TOWN" : "LIVERPOOL",
      "POSTCODE" : "L1 4AR",
      "RPC" : "2",
      "X_COORDINATE" : 334958.0,
      "Y_COORDINATE" : 390015.0,
      "STATUS" : "APPROVED",
      "LOGICAL_STATUS_CODE" : "1",
      "CLASSIFICATION_CODE" : "CR08",
      "CLASSIFICATION_CODE_DESCRIPTION" : "Shop / Showroom",
      "LOCAL_CUSTODIAN_CODE" : 4310,
      "LOCAL_CUSTODIAN_CODE_DESCRIPTION" : "LIVERPOOL",
      "POSTAL_ADDRESS_CODE" : "D",
      "POSTAL_ADDRESS_CODE_DESCRIPTION" : "A record which is linked to PAF",
      "BLPU_STATE_CODE" : null,
      "BLPU_STATE_CODE_DESCRIPTION" : "Unknown/Not applicable",
      "TOPOGRAPHY_LAYER_TOID" : "osgb1000034933459",
      "PARENT_UPRN" : "38057465",
      "LAST_UPDATE_DATE" : "10/02/2016",
      "ENTRY_DATE" : "13/07/2009",
      "LANGUAGE" : "EN",
      "MATCH" : 1.0,
      "MATCH_DESCRIPTION" : "EXACT"
    }
  }, {
    "DPA" : {
      "UPRN" : "38283115",
      "UDPRN" : "51755032",
      "ADDRESS" : "UNIT 306, VANILLA FACTORY, 39, FLEET STREET, LIVERPOOL, L1 4AR",
      "SUB_BUILDING_NAME" : "UNIT 306",
      "BUILDING_NAME" : "VANILLA FACTORY",
      "BUILDING_NUMBER" : "39",
      "THOROUGHFARE_NAME" : "FLEET STREET",
      "POST_TOWN" : "LIVERPOOL",
      "POSTCODE" : "L1 4AR",
      "RPC" : "2",
      "X_COORDINATE" : 334958.0,
      "Y_COORDINATE" : 390015.0,
      "STATUS" : "APPROVED",
      "LOGICAL_STATUS_CODE" : "1",
      "CLASSIFICATION_CODE" : "CR08",
      "CLASSIFICATION_CODE_DESCRIPTION" : "Shop / Showroom",
      "LOCAL_CUSTODIAN_CODE" : 4310,
      "LOCAL_CUSTODIAN_CODE_DESCRIPTION" : "LIVERPOOL",
      "POSTAL_ADDRESS_CODE" : "D",
      "POSTAL_ADDRESS_CODE_DESCRIPTION" : "A record which is linked to PAF",
      "BLPU_STATE_CODE" : null,
      "BLPU_STATE_CODE_DESCRIPTION" : "Unknown/Not applicable",
      "TOPOGRAPHY_LAYER_TOID" : "osgb1000034933459",
      "PARENT_UPRN" : "38057465",
      "LAST_UPDATE_DATE" : "10/02/2016",
      "ENTRY_DATE" : "13/07/2009",
      "LANGUAGE" : "EN",
      "MATCH" : 1.0,
      "MATCH_DESCRIPTION" : "EXACT"
    }
  }, {
    "DPA" : {
      "UPRN" : "38283116",
      "UDPRN" : "51755036",
      "ADDRESS" : "UNIT 307, VANILLA FACTORY, 39, FLEET STREET, LIVERPOOL, L1 4AR",
      "SUB_BUILDING_NAME" : "UNIT 307",
      "BUILDING_NAME" : "VANILLA FACTORY",
      "BUILDING_NUMBER" : "39",
      "THOROUGHFARE_NAME" : "FLEET STREET",
      "POST_TOWN" : "LIVERPOOL",
      "POSTCODE" : "L1 4AR",
      "RPC" : "2",
      "X_COORDINATE" : 334958.0,
      "Y_COORDINATE" : 390015.0,
      "STATUS" : "APPROVED",
      "LOGICAL_STATUS_CODE" : "1",
      "CLASSIFICATION_CODE" : "CR08",
      "CLASSIFICATION_CODE_DESCRIPTION" : "Shop / Showroom",
      "LOCAL_CUSTODIAN_CODE" : 4310,
      "LOCAL_CUSTODIAN_CODE_DESCRIPTION" : "LIVERPOOL",
      "POSTAL_ADDRESS_CODE" : "D",
      "POSTAL_ADDRESS_CODE_DESCRIPTION" : "A record which is linked to PAF",
      "BLPU_STATE_CODE" : null,
      "BLPU_STATE_CODE_DESCRIPTION" : "Unknown/Not applicable",
      "TOPOGRAPHY_LAYER_TOID" : "osgb1000034933459",
      "PARENT_UPRN" : "38057465",
      "LAST_UPDATE_DATE" : "10/02/2016",
      "ENTRY_DATE" : "13/07/2009",
      "LANGUAGE" : "EN",
      "MATCH" : 1.0,
      "MATCH_DESCRIPTION" : "EXACT"
    }
  }, {
    "DPA" : {
      "UPRN" : "38283118",
      "UDPRN" : "51755028",
      "ADDRESS" : "UNIT 309, VANILLA FACTORY, 39, FLEET STREET, LIVERPOOL, L1 4AR",
      "SUB_BUILDING_NAME" : "UNIT 309",
      "BUILDING_NAME" : "VANILLA FACTORY",
      "BUILDING_NUMBER" : "39",
      "THOROUGHFARE_NAME" : "FLEET STREET",
      "POST_TOWN" : "LIVERPOOL",
      "POSTCODE" : "L1 4AR",
      "RPC" : "2",
      "X_COORDINATE" : 334958.0,
      "Y_COORDINATE" : 390015.0,
      "STATUS" : "APPROVED",
      "LOGICAL_STATUS_CODE" : "1",
      "CLASSIFICATION_CODE" : "CR08",
      "CLASSIFICATION_CODE_DESCRIPTION" : "Shop / Showroom",
      "LOCAL_CUSTODIAN_CODE" : 4310,
      "LOCAL_CUSTODIAN_CODE_DESCRIPTION" : "LIVERPOOL",
      "POSTAL_ADDRESS_CODE" : "D",
      "POSTAL_ADDRESS_CODE_DESCRIPTION" : "A record which is linked to PAF",
      "BLPU_STATE_CODE" : null,
      "BLPU_STATE_CODE_DESCRIPTION" : "Unknown/Not applicable",
      "TOPOGRAPHY_LAYER_TOID" : "osgb1000034933459",
      "PARENT_UPRN" : "38057465",
      "LAST_UPDATE_DATE" : "10/02/2016",
      "ENTRY_DATE" : "13/07/2009",
      "LANGUAGE" : "EN",
      "MATCH" : 1.0,
      "MATCH_DESCRIPTION" : "EXACT"
    }
  }, {
    "DPA" : {
      "UPRN" : "38292402",
      "UDPRN" : "28585955",
      "ADDRESS" : "HARVEY GUINAN, UNIT 310-311, VANILLA FACTORY, 39, FLEET STREET, LIVERPOOL, L1 4AR",
      "ORGANISATION_NAME" : "HARVEY GUINAN",
      "SUB_BUILDING_NAME" : "UNIT 310-311",
      "BUILDING_NAME" : "VANILLA FACTORY",
      "BUILDING_NUMBER" : "39",
      "THOROUGHFARE_NAME" : "FLEET STREET",
      "POST_TOWN" : "LIVERPOOL",
      "POSTCODE" : "L1 4AR",
      "RPC" : "2",
      "X_COORDINATE" : 334958.0,
      "Y_COORDINATE" : 390015.0,
      "STATUS" : "APPROVED",
      "LOGICAL_STATUS_CODE" : "1",
      "CLASSIFICATION_CODE" : "CO01",
      "CLASSIFICATION_CODE_DESCRIPTION" : "Office / Work Studio",
      "LOCAL_CUSTODIAN_CODE" : 4310,
      "LOCAL_CUSTODIAN_CODE_DESCRIPTION" : "LIVERPOOL",
      "POSTAL_ADDRESS_CODE" : "D",
      "POSTAL_ADDRESS_CODE_DESCRIPTION" : "A record which is linked to PAF",
      "BLPU_STATE_CODE" : null,
      "BLPU_STATE_CODE_DESCRIPTION" : "Unknown/Not applicable",
      "TOPOGRAPHY_LAYER_TOID" : "osgb1000034933459",
      "PARENT_UPRN" : "38057465",
      "LAST_UPDATE_DATE" : "10/02/2016",
      "ENTRY_DATE" : "20/07/2011",
      "LANGUAGE" : "EN",
      "MATCH" : 1.0,
      "MATCH_DESCRIPTION" : "EXACT"
    }
  }, {
    "DPA" : {
      "UPRN" : "38283122",
      "UDPRN" : "51755030",
      "ADDRESS" : "UNIT 400, VANILLA FACTORY, 39, FLEET STREET, LIVERPOOL, L1 4AR",
      "SUB_BUILDING_NAME" : "UNIT 400",
      "BUILDING_NAME" : "VANILLA FACTORY",
      "BUILDING_NUMBER" : "39",
      "THOROUGHFARE_NAME" : "FLEET STREET",
      "POST_TOWN" : "LIVERPOOL",
      "POSTCODE" : "L1 4AR",
      "RPC" : "2",
      "X_COORDINATE" : 334958.0,
      "Y_COORDINATE" : 390015.0,
      "STATUS" : "APPROVED",
      "LOGICAL_STATUS_CODE" : "1",
      "CLASSIFICATION_CODE" : "CO01",
      "CLASSIFICATION_CODE_DESCRIPTION" : "Office / Work Studio",
      "LOCAL_CUSTODIAN_CODE" : 4310,
      "LOCAL_CUSTODIAN_CODE_DESCRIPTION" : "LIVERPOOL",
      "POSTAL_ADDRESS_CODE" : "D",
      "POSTAL_ADDRESS_CODE_DESCRIPTION" : "A record which is linked to PAF",
      "BLPU_STATE_CODE" : null,
      "BLPU_STATE_CODE_DESCRIPTION" : "Unknown/Not applicable",
      "TOPOGRAPHY_LAYER_TOID" : "osgb1000034933459",
      "PARENT_UPRN" : "38057465",
      "LAST_UPDATE_DATE" : "12/11/2018",
      "ENTRY_DATE" : "13/07/2009",
      "LANGUAGE" : "EN",
      "MATCH" : 1.0,
      "MATCH_DESCRIPTION" : "EXACT"
    }
  }, {
    "DPA" : {
      "UPRN" : "38214548",
      "UDPRN" : "12489029",
      "ADDRESS" : "REVOLUTION, 47, FLEET STREET, LIVERPOOL, L1 4AR",
      "ORGANISATION_NAME" : "REVOLUTION",
      "BUILDING_NUMBER" : "47",
      "THOROUGHFARE_NAME" : "FLEET STREET",
      "POST_TOWN" : "LIVERPOOL",
      "POSTCODE" : "L1 4AR",
      "RPC" : "2",
      "X_COORDINATE" : 334877.0,
      "Y_COORDINATE" : 390110.0,
      "STATUS" : "APPROVED",
      "LOGICAL_STATUS_CODE" : "1",
      "CLASSIFICATION_CODE" : "CR06",
      "CLASSIFICATION_CODE_DESCRIPTION" : "Public House / Bar / Nightclub",
      "LOCAL_CUSTODIAN_CODE" : 4310,
      "LOCAL_CUSTODIAN_CODE_DESCRIPTION" : "LIVERPOOL",
      "POSTAL_ADDRESS_CODE" : "D",
      "POSTAL_ADDRESS_CODE_DESCRIPTION" : "A record which is linked to PAF",
      "BLPU_STATE_CODE" : "2",
      "BLPU_STATE_CODE_DESCRIPTION" : "In use",
      "TOPOGRAPHY_LAYER_TOID" : "osgb1000034933542",
      "PARENT_UPRN" : "38220889",
      "LAST_UPDATE_DATE" : "12/11/2018",
      "ENTRY_DATE" : "25/05/2001",
      "BLPU_STATE_DATE" : "27/02/2012",
      "LANGUAGE" : "EN",
      "MATCH" : 1.0,
      "MATCH_DESCRIPTION" : "EXACT"
    }
  }, {
    "DPA" : {
      "UPRN" : "38057459",
      "UDPRN" : "12489016",
      "ADDRESS" : "3A, FLEET STREET, LIVERPOOL, L1 4AR",
      "BUILDING_NAME" : "3A",
      "THOROUGHFARE_NAME" : "FLEET STREET",
      "POST_TOWN" : "LIVERPOOL",
      "POSTCODE" : "L1 4AR",
      "RPC" : "1",
      "X_COORDINATE" : 334813.0,
      "Y_COORDINATE" : 390140.0,
      "STATUS" : "APPROVED",
      "LOGICAL_STATUS_CODE" : "1",
      "CLASSIFICATION_CODE" : "CI04",
      "CLASSIFICATION_CODE_DESCRIPTION" : "Warehouse / Store / Storage Depot",
      "LOCAL_CUSTODIAN_CODE" : 4310,
      "LOCAL_CUSTODIAN_CODE_DESCRIPTION" : "LIVERPOOL",
      "POSTAL_ADDRESS_CODE" : "D",
      "POSTAL_ADDRESS_CODE_DESCRIPTION" : "A record which is linked to PAF",
      "BLPU_STATE_CODE" : null,
      "BLPU_STATE_CODE_DESCRIPTION" : "Unknown/Not applicable",
      "TOPOGRAPHY_LAYER_TOID" : "osgb1000034933537",
      "LAST_UPDATE_DATE" : "10/02/2016",
      "ENTRY_DATE" : "07/07/1997",
      "LANGUAGE" : "EN",
      "MATCH" : 1.0,
      "MATCH_DESCRIPTION" : "EXACT"
    }
  }, {
    "DPA" : {
      "UPRN" : "38057466",
      "UDPRN" : "12489015",
      "ADDRESS" : "43-45, FLEET STREET, LIVERPOOL, L1 4AR",
      "BUILDING_NAME" : "43-45",
      "THOROUGHFARE_NAME" : "FLEET STREET",
      "POST_TOWN" : "LIVERPOOL",
      "POSTCODE" : "L1 4AR",
      "RPC" : "2",
      "X_COORDINATE" : 334971.0,
      "Y_COORDINATE" : 390005.0,
      "STATUS" : "APPROVED",
      "LOGICAL_STATUS_CODE" : "1",
      "CLASSIFICATION_CODE" : "CR06",
      "CLASSIFICATION_CODE_DESCRIPTION" : "Public House / Bar / Nightclub",
      "LOCAL_CUSTODIAN_CODE" : 4310,
      "LOCAL_CUSTODIAN_CODE_DESCRIPTION" : "LIVERPOOL",
      "POSTAL_ADDRESS_CODE" : "D",
      "POSTAL_ADDRESS_CODE_DESCRIPTION" : "A record which is linked to PAF",
      "BLPU_STATE_CODE" : null,
      "BLPU_STATE_CODE_DESCRIPTION" : "Unknown/Not applicable",
      "TOPOGRAPHY_LAYER_TOID" : "osgb1000034933457",
      "LAST_UPDATE_DATE" : "12/11/2018",
      "ENTRY_DATE" : "07/07/1997",
      "LANGUAGE" : "EN",
      "MATCH" : 1.0,
      "MATCH_DESCRIPTION" : "EXACT"
    }
  }, {
    "DPA" : {
      "UPRN" : "38250275",
      "UDPRN" : "28684570",
      "ADDRESS" : "APARTMENT 1, THE JAM WORKS 49-51, FLEET STREET, LIVERPOOL, L1 4AR",
      "SUB_BUILDING_NAME" : "APARTMENT 1",
      "BUILDING_NAME" : "THE JAM WORKS 49-51",
      "THOROUGHFARE_NAME" : "FLEET STREET",
      "POST_TOWN" : "LIVERPOOL",
      "POSTCODE" : "L1 4AR",
      "RPC" : "2",
      "X_COORDINATE" : 335018.0,
      "Y_COORDINATE" : 389970.0,
      "STATUS" : "APPROVED",
      "LOGICAL_STATUS_CODE" : "1",
      "CLASSIFICATION_CODE" : "RD06",
      "CLASSIFICATION_CODE_DESCRIPTION" : "Self Contained Flat (Includes Maisonette / Apartment)",
      "LOCAL_CUSTODIAN_CODE" : 4310,
      "LOCAL_CUSTODIAN_CODE_DESCRIPTION" : "LIVERPOOL",
      "POSTAL_ADDRESS_CODE" : "D",
      "POSTAL_ADDRESS_CODE_DESCRIPTION" : "A record which is linked to PAF",
      "BLPU_STATE_CODE" : null,
      "BLPU_STATE_CODE_DESCRIPTION" : "Unknown/Not applicable",
      "TOPOGRAPHY_LAYER_TOID" : "osgb1000002730053081",
      "PARENT_UPRN" : "38249360",
      "LAST_UPDATE_DATE" : "10/02/2016",
      "ENTRY_DATE" : "04/04/2008",
      "LANGUAGE" : "EN",
      "MATCH" : 1.0,
      "MATCH_DESCRIPTION" : "EXACT"
    }
  }, {
    "DPA" : {
      "UPRN" : "38250284",
      "UDPRN" : "28684579",
      "ADDRESS" : "APARTMENT 10, THE JAM WORKS 49-51, FLEET STREET, LIVERPOOL, L1 4AR",
      "SUB_BUILDING_NAME" : "APARTMENT 10",
      "BUILDING_NAME" : "THE JAM WORKS 49-51",
      "THOROUGHFARE_NAME" : "FLEET STREET",
      "POST_TOWN" : "LIVERPOOL",
      "POSTCODE" : "L1 4AR",
      "RPC" : "2",
      "X_COORDINATE" : 335018.0,
      "Y_COORDINATE" : 389970.0,
      "STATUS" : "APPROVED",
      "LOGICAL_STATUS_CODE" : "1",
      "CLASSIFICATION_CODE" : "RD06",
      "CLASSIFICATION_CODE_DESCRIPTION" : "Self Contained Flat (Includes Maisonette / Apartment)",
      "LOCAL_CUSTODIAN_CODE" : 4310,
      "LOCAL_CUSTODIAN_CODE_DESCRIPTION" : "LIVERPOOL",
      "POSTAL_ADDRESS_CODE" : "D",
      "POSTAL_ADDRESS_CODE_DESCRIPTION" : "A record which is linked to PAF",
      "BLPU_STATE_CODE" : null,
      "BLPU_STATE_CODE_DESCRIPTION" : "Unknown/Not applicable",
      "TOPOGRAPHY_LAYER_TOID" : "osgb1000002730053081",
      "PARENT_UPRN" : "38249360",
      "LAST_UPDATE_DATE" : "10/02/2016",
      "ENTRY_DATE" : "04/04/2008",
      "LANGUAGE" : "EN",
      "MATCH" : 1.0,
      "MATCH_DESCRIPTION" : "EXACT"
    }
  }, {
    "DPA" : {
      "UPRN" : "38250285",
      "UDPRN" : "28684580",
      "ADDRESS" : "APARTMENT 11, THE JAM WORKS 49-51, FLEET STREET, LIVERPOOL, L1 4AR",
      "SUB_BUILDING_NAME" : "APARTMENT 11",
      "BUILDING_NAME" : "THE JAM WORKS 49-51",
      "THOROUGHFARE_NAME" : "FLEET STREET",
      "POST_TOWN" : "LIVERPOOL",
      "POSTCODE" : "L1 4AR",
      "RPC" : "2",
      "X_COORDINATE" : 335018.0,
      "Y_COORDINATE" : 389970.0,
      "STATUS" : "APPROVED",
      "LOGICAL_STATUS_CODE" : "1",
      "CLASSIFICATION_CODE" : "RD06",
      "CLASSIFICATION_CODE_DESCRIPTION" : "Self Contained Flat (Includes Maisonette / Apartment)",
      "LOCAL_CUSTODIAN_CODE" : 4310,
      "LOCAL_CUSTODIAN_CODE_DESCRIPTION" : "LIVERPOOL",
      "POSTAL_ADDRESS_CODE" : "D",
      "POSTAL_ADDRESS_CODE_DESCRIPTION" : "A record which is linked to PAF",
      "BLPU_STATE_CODE" : null,
      "BLPU_STATE_CODE_DESCRIPTION" : "Unknown/Not applicable",
      "TOPOGRAPHY_LAYER_TOID" : "osgb1000002730053081",
      "PARENT_UPRN" : "38249360",
      "LAST_UPDATE_DATE" : "10/02/2016",
      "ENTRY_DATE" : "04/04/2008",
      "LANGUAGE" : "EN",
      "MATCH" : 1.0,
      "MATCH_DESCRIPTION" : "EXACT"
    }
  }, {
    "DPA" : {
      "UPRN" : "38250286",
      "UDPRN" : "28684581",
      "ADDRESS" : "APARTMENT 12, THE JAM WORKS 49-51, FLEET STREET, LIVERPOOL, L1 4AR",
      "SUB_BUILDING_NAME" : "APARTMENT 12",
      "BUILDING_NAME" : "THE JAM WORKS 49-51",
      "THOROUGHFARE_NAME" : "FLEET STREET",
      "POST_TOWN" : "LIVERPOOL",
      "POSTCODE" : "L1 4AR",
      "RPC" : "2",
      "X_COORDINATE" : 335018.0,
      "Y_COORDINATE" : 389970.0,
      "STATUS" : "APPROVED",
      "LOGICAL_STATUS_CODE" : "1",
      "CLASSIFICATION_CODE" : "RD06",
      "CLASSIFICATION_CODE_DESCRIPTION" : "Self Contained Flat (Includes Maisonette / Apartment)",
      "LOCAL_CUSTODIAN_CODE" : 4310,
      "LOCAL_CUSTODIAN_CODE_DESCRIPTION" : "LIVERPOOL",
      "POSTAL_ADDRESS_CODE" : "D",
      "POSTAL_ADDRESS_CODE_DESCRIPTION" : "A record which is linked to PAF",
      "BLPU_STATE_CODE" : null,
      "BLPU_STATE_CODE_DESCRIPTION" : "Unknown/Not applicable",
      "TOPOGRAPHY_LAYER_TOID" : "osgb1000002730053081",
      "PARENT_UPRN" : "38249360",
      "LAST_UPDATE_DATE" : "10/02/2016",
      "ENTRY_DATE" : "04/04/2008",
      "LANGUAGE" : "EN",
      "MATCH" : 1.0,
      "MATCH_DESCRIPTION" : "EXACT"
    }
  }, {
    "DPA" : {
      "UPRN" : "38250287",
      "UDPRN" : "28684583",
      "ADDRESS" : "APARTMENT 14, THE JAM WORKS 49-51, FLEET STREET, LIVERPOOL, L1 4AR",
      "SUB_BUILDING_NAME" : "APARTMENT 14",
      "BUILDING_NAME" : "THE JAM WORKS 49-51",
      "THOROUGHFARE_NAME" : "FLEET STREET",
      "POST_TOWN" : "LIVERPOOL",
      "POSTCODE" : "L1 4AR",
      "RPC" : "2",
      "X_COORDINATE" : 335018.0,
      "Y_COORDINATE" : 389970.0,
      "STATUS" : "APPROVED",
      "LOGICAL_STATUS_CODE" : "1",
      "CLASSIFICATION_CODE" : "RD06",
      "CLASSIFICATION_CODE_DESCRIPTION" : "Self Contained Flat (Includes Maisonette / Apartment)",
      "LOCAL_CUSTODIAN_CODE" : 4310,
      "LOCAL_CUSTODIAN_CODE_DESCRIPTION" : "LIVERPOOL",
      "POSTAL_ADDRESS_CODE" : "D",
      "POSTAL_ADDRESS_CODE_DESCRIPTION" : "A record which is linked to PAF",
      "BLPU_STATE_CODE" : null,
      "BLPU_STATE_CODE_DESCRIPTION" : "Unknown/Not applicable",
      "TOPOGRAPHY_LAYER_TOID" : "osgb1000002730053081",
      "PARENT_UPRN" : "38249360",
      "LAST_UPDATE_DATE" : "10/02/2016",
      "ENTRY_DATE" : "04/04/2008",
      "LANGUAGE" : "EN",
      "MATCH" : 1.0,
      "MATCH_DESCRIPTION" : "EXACT"
    }
  }, {
    "DPA" : {
      "UPRN" : "38250288",
      "UDPRN" : "28684584",
      "ADDRESS" : "APARTMENT 15, THE JAM WORKS 49-51, FLEET STREET, LIVERPOOL, L1 4AR",
      "SUB_BUILDING_NAME" : "APARTMENT 15",
      "BUILDING_NAME" : "THE JAM WORKS 49-51",
      "THOROUGHFARE_NAME" : "FLEET STREET",
      "POST_TOWN" : "LIVERPOOL",
      "POSTCODE" : "L1 4AR",
      "RPC" : "2",
      "X_COORDINATE" : 335018.0,
      "Y_COORDINATE" : 389970.0,
      "STATUS" : "APPROVED",
      "LOGICAL_STATUS_CODE" : "1",
      "CLASSIFICATION_CODE" : "RD06",
      "CLASSIFICATION_CODE_DESCRIPTION" : "Self Contained Flat (Includes Maisonette / Apartment)",
      "LOCAL_CUSTODIAN_CODE" : 4310,
      "LOCAL_CUSTODIAN_CODE_DESCRIPTION" : "LIVERPOOL",
      "POSTAL_ADDRESS_CODE" : "D",
      "POSTAL_ADDRESS_CODE_DESCRIPTION" : "A record which is linked to PAF",
      "BLPU_STATE_CODE" : null,
      "BLPU_STATE_CODE_DESCRIPTION" : "Unknown/Not applicable",
      "TOPOGRAPHY_LAYER_TOID" : "osgb1000002730053081",
      "PARENT_UPRN" : "38249360",
      "LAST_UPDATE_DATE" : "10/02/2016",
      "ENTRY_DATE" : "04/04/2008",
      "LANGUAGE" : "EN",
      "MATCH" : 1.0,
      "MATCH_DESCRIPTION" : "EXACT"
    }
  }, {
    "DPA" : {
      "UPRN" : "38250289",
      "UDPRN" : "28684585",
      "ADDRESS" : "APARTMENT 16, THE JAM WORKS 49-51, FLEET STREET, LIVERPOOL, L1 4AR",
      "SUB_BUILDING_NAME" : "APARTMENT 16",
      "BUILDING_NAME" : "THE JAM WORKS 49-51",
      "THOROUGHFARE_NAME" : "FLEET STREET",
      "POST_TOWN" : "LIVERPOOL",
      "POSTCODE" : "L1 4AR",
      "RPC" : "2",
      "X_COORDINATE" : 335018.0,
      "Y_COORDINATE" : 389970.0,
      "STATUS" : "APPROVED",
      "LOGICAL_STATUS_CODE" : "1",
      "CLASSIFICATION_CODE" : "RD06",
      "CLASSIFICATION_CODE_DESCRIPTION" : "Self Contained Flat (Includes Maisonette / Apartment)",
      "LOCAL_CUSTODIAN_CODE" : 4310,
      "LOCAL_CUSTODIAN_CODE_DESCRIPTION" : "LIVERPOOL",
      "POSTAL_ADDRESS_CODE" : "D",
      "POSTAL_ADDRESS_CODE_DESCRIPTION" : "A record which is linked to PAF",
      "BLPU_STATE_CODE" : null,
      "BLPU_STATE_CODE_DESCRIPTION" : "Unknown/Not applicable",
      "TOPOGRAPHY_LAYER_TOID" : "osgb1000002730053081",
      "PARENT_UPRN" : "38249360",
      "LAST_UPDATE_DATE" : "10/02/2016",
      "ENTRY_DATE" : "04/04/2008",
      "LANGUAGE" : "EN",
      "MATCH" : 1.0,
      "MATCH_DESCRIPTION" : "EXACT"
    }
  }, {
    "DPA" : {
      "UPRN" : "38250290",
      "UDPRN" : "28684586",
      "ADDRESS" : "APARTMENT 17, THE JAM WORKS 49-51, FLEET STREET, LIVERPOOL, L1 4AR",
      "SUB_BUILDING_NAME" : "APARTMENT 17",
      "BUILDING_NAME" : "THE JAM WORKS 49-51",
      "THOROUGHFARE_NAME" : "FLEET STREET",
      "POST_TOWN" : "LIVERPOOL",
      "POSTCODE" : "L1 4AR",
      "RPC" : "2",
      "X_COORDINATE" : 335018.0,
      "Y_COORDINATE" : 389970.0,
      "STATUS" : "APPROVED",
      "LOGICAL_STATUS_CODE" : "1",
      "CLASSIFICATION_CODE" : "RD06",
      "CLASSIFICATION_CODE_DESCRIPTION" : "Self Contained Flat (Includes Maisonette / Apartment)",
      "LOCAL_CUSTODIAN_CODE" : 4310,
      "LOCAL_CUSTODIAN_CODE_DESCRIPTION" : "LIVERPOOL",
      "POSTAL_ADDRESS_CODE" : "D",
      "POSTAL_ADDRESS_CODE_DESCRIPTION" : "A record which is linked to PAF",
      "BLPU_STATE_CODE" : null,
      "BLPU_STATE_CODE_DESCRIPTION" : "Unknown/Not applicable",
      "TOPOGRAPHY_LAYER_TOID" : "osgb1000002730053081",
      "PARENT_UPRN" : "38249360",
      "LAST_UPDATE_DATE" : "10/02/2016",
      "ENTRY_DATE" : "04/04/2008",
      "LANGUAGE" : "EN",
      "MATCH" : 1.0,
      "MATCH_DESCRIPTION" : "EXACT"
    }
  }, {
    "DPA" : {
      "UPRN" : "38250291",
      "UDPRN" : "28684587",
      "ADDRESS" : "APARTMENT 18, THE JAM WORKS 49-51, FLEET STREET, LIVERPOOL, L1 4AR",
      "SUB_BUILDING_NAME" : "APARTMENT 18",
      "BUILDING_NAME" : "THE JAM WORKS 49-51",
      "THOROUGHFARE_NAME" : "FLEET STREET",
      "POST_TOWN" : "LIVERPOOL",
      "POSTCODE" : "L1 4AR",
      "RPC" : "2",
      "X_COORDINATE" : 335018.0,
      "Y_COORDINATE" : 389970.0,
      "STATUS" : "APPROVED",
      "LOGICAL_STATUS_CODE" : "1",
      "CLASSIFICATION_CODE" : "RD06",
      "CLASSIFICATION_CODE_DESCRIPTION" : "Self Contained Flat (Includes Maisonette / Apartment)",
      "LOCAL_CUSTODIAN_CODE" : 4310,
      "LOCAL_CUSTODIAN_CODE_DESCRIPTION" : "LIVERPOOL",
      "POSTAL_ADDRESS_CODE" : "D",
      "POSTAL_ADDRESS_CODE_DESCRIPTION" : "A record which is linked to PAF",
      "BLPU_STATE_CODE" : null,
      "BLPU_STATE_CODE_DESCRIPTION" : "Unknown/Not applicable",
      "TOPOGRAPHY_LAYER_TOID" : "osgb1000002730053081",
      "PARENT_UPRN" : "38249360",
      "LAST_UPDATE_DATE" : "10/02/2016",
      "ENTRY_DATE" : "04/04/2008",
      "LANGUAGE" : "EN",
      "MATCH" : 1.0,
      "MATCH_DESCRIPTION" : "EXACT"
    }
  }, {
    "DPA" : {
      "UPRN" : "38250292",
      "UDPRN" : "28684588",
      "ADDRESS" : "APARTMENT 19, THE JAM WORKS 49-51, FLEET STREET, LIVERPOOL, L1 4AR",
      "SUB_BUILDING_NAME" : "APARTMENT 19",
      "BUILDING_NAME" : "THE JAM WORKS 49-51",
      "THOROUGHFARE_NAME" : "FLEET STREET",
      "POST_TOWN" : "LIVERPOOL",
      "POSTCODE" : "L1 4AR",
      "RPC" : "2",
      "X_COORDINATE" : 335018.0,
      "Y_COORDINATE" : 389970.0,
      "STATUS" : "APPROVED",
      "LOGICAL_STATUS_CODE" : "1",
      "CLASSIFICATION_CODE" : "RD06",
      "CLASSIFICATION_CODE_DESCRIPTION" : "Self Contained Flat (Includes Maisonette / Apartment)",
      "LOCAL_CUSTODIAN_CODE" : 4310,
      "LOCAL_CUSTODIAN_CODE_DESCRIPTION" : "LIVERPOOL",
      "POSTAL_ADDRESS_CODE" : "D",
      "POSTAL_ADDRESS_CODE_DESCRIPTION" : "A record which is linked to PAF",
      "BLPU_STATE_CODE" : null,
      "BLPU_STATE_CODE_DESCRIPTION" : "Unknown/Not applicable",
      "TOPOGRAPHY_LAYER_TOID" : "osgb1000002730053081",
      "PARENT_UPRN" : "38249360",
      "LAST_UPDATE_DATE" : "10/02/2016",
      "ENTRY_DATE" : "04/04/2008",
      "LANGUAGE" : "EN",
      "MATCH" : 1.0,
      "MATCH_DESCRIPTION" : "EXACT"
    }
  }, {
    "DPA" : {
      "UPRN" : "38250276",
      "UDPRN" : "28684571",
      "ADDRESS" : "APARTMENT 2, THE JAM WORKS 49-51, FLEET STREET, LIVERPOOL, L1 4AR",
      "SUB_BUILDING_NAME" : "APARTMENT 2",
      "BUILDING_NAME" : "THE JAM WORKS 49-51",
      "THOROUGHFARE_NAME" : "FLEET STREET",
      "POST_TOWN" : "LIVERPOOL",
      "POSTCODE" : "L1 4AR",
      "RPC" : "2",
      "X_COORDINATE" : 335018.0,
      "Y_COORDINATE" : 389970.0,
      "STATUS" : "APPROVED",
      "LOGICAL_STATUS_CODE" : "1",
      "CLASSIFICATION_CODE" : "RD06",
      "CLASSIFICATION_CODE_DESCRIPTION" : "Self Contained Flat (Includes Maisonette / Apartment)",
      "LOCAL_CUSTODIAN_CODE" : 4310,
      "LOCAL_CUSTODIAN_CODE_DESCRIPTION" : "LIVERPOOL",
      "POSTAL_ADDRESS_CODE" : "D",
      "POSTAL_ADDRESS_CODE_DESCRIPTION" : "A record which is linked to PAF",
      "BLPU_STATE_CODE" : null,
      "BLPU_STATE_CODE_DESCRIPTION" : "Unknown/Not applicable",
      "TOPOGRAPHY_LAYER_TOID" : "osgb1000002730053081",
      "PARENT_UPRN" : "38249360",
      "LAST_UPDATE_DATE" : "10/02/2016",
      "ENTRY_DATE" : "04/04/2008",
      "LANGUAGE" : "EN",
      "MATCH" : 1.0,
      "MATCH_DESCRIPTION" : "EXACT"
    }
  }, {
    "DPA" : {
      "UPRN" : "38250293",
      "UDPRN" : "28684589",
      "ADDRESS" : "APARTMENT 20, THE JAM WORKS 49-51, FLEET STREET, LIVERPOOL, L1 4AR",
      "SUB_BUILDING_NAME" : "APARTMENT 20",
      "BUILDING_NAME" : "THE JAM WORKS 49-51",
      "THOROUGHFARE_NAME" : "FLEET STREET",
      "POST_TOWN" : "LIVERPOOL",
      "POSTCODE" : "L1 4AR",
      "RPC" : "2",
      "X_COORDINATE" : 335018.0,
      "Y_COORDINATE" : 389970.0,
      "STATUS" : "APPROVED",
      "LOGICAL_STATUS_CODE" : "1",
      "CLASSIFICATION_CODE" : "RD06",
      "CLASSIFICATION_CODE_DESCRIPTION" : "Self Contained Flat (Includes Maisonette / Apartment)",
      "LOCAL_CUSTODIAN_CODE" : 4310,
      "LOCAL_CUSTODIAN_CODE_DESCRIPTION" : "LIVERPOOL",
      "POSTAL_ADDRESS_CODE" : "D",
      "POSTAL_ADDRESS_CODE_DESCRIPTION" : "A record which is linked to PAF",
      "BLPU_STATE_CODE" : null,
      "BLPU_STATE_CODE_DESCRIPTION" : "Unknown/Not applicable",
      "TOPOGRAPHY_LAYER_TOID" : "osgb1000002730053081",
      "PARENT_UPRN" : "38249360",
      "LAST_UPDATE_DATE" : "10/02/2016",
      "ENTRY_DATE" : "04/04/2008",
      "LANGUAGE" : "EN",
      "MATCH" : 1.0,
      "MATCH_DESCRIPTION" : "EXACT"
    }
  }, {
    "DPA" : {
      "UPRN" : "38250294",
      "UDPRN" : "28684590",
      "ADDRESS" : "APARTMENT 21, THE JAM WORKS 49-51, FLEET STREET, LIVERPOOL, L1 4AR",
      "SUB_BUILDING_NAME" : "APARTMENT 21",
      "BUILDING_NAME" : "THE JAM WORKS 49-51",
      "THOROUGHFARE_NAME" : "FLEET STREET",
      "POST_TOWN" : "LIVERPOOL",
      "POSTCODE" : "L1 4AR",
      "RPC" : "2",
      "X_COORDINATE" : 335018.0,
      "Y_COORDINATE" : 389970.0,
      "STATUS" : "APPROVED",
      "LOGICAL_STATUS_CODE" : "1",
      "CLASSIFICATION_CODE" : "RD06",
      "CLASSIFICATION_CODE_DESCRIPTION" : "Self Contained Flat (Includes Maisonette / Apartment)",
      "LOCAL_CUSTODIAN_CODE" : 4310,
      "LOCAL_CUSTODIAN_CODE_DESCRIPTION" : "LIVERPOOL",
      "POSTAL_ADDRESS_CODE" : "D",
      "POSTAL_ADDRESS_CODE_DESCRIPTION" : "A record which is linked to PAF",
      "BLPU_STATE_CODE" : null,
      "BLPU_STATE_CODE_DESCRIPTION" : "Unknown/Not applicable",
      "TOPOGRAPHY_LAYER_TOID" : "osgb1000002730053081",
      "PARENT_UPRN" : "38249360",
      "LAST_UPDATE_DATE" : "10/02/2016",
      "ENTRY_DATE" : "04/04/2008",
      "LANGUAGE" : "EN",
      "MATCH" : 1.0,
      "MATCH_DESCRIPTION" : "EXACT"
    }
  }, {
    "DPA" : {
      "UPRN" : "38250295",
      "UDPRN" : "28684591",
      "ADDRESS" : "APARTMENT 22, THE JAM WORKS 49-51, FLEET STREET, LIVERPOOL, L1 4AR",
      "SUB_BUILDING_NAME" : "APARTMENT 22",
      "BUILDING_NAME" : "THE JAM WORKS 49-51",
      "THOROUGHFARE_NAME" : "FLEET STREET",
      "POST_TOWN" : "LIVERPOOL",
      "POSTCODE" : "L1 4AR",
      "RPC" : "2",
      "X_COORDINATE" : 335018.0,
      "Y_COORDINATE" : 389970.0,
      "STATUS" : "APPROVED",
      "LOGICAL_STATUS_CODE" : "1",
      "CLASSIFICATION_CODE" : "RD06",
      "CLASSIFICATION_CODE_DESCRIPTION" : "Self Contained Flat (Includes Maisonette / Apartment)",
      "LOCAL_CUSTODIAN_CODE" : 4310,
      "LOCAL_CUSTODIAN_CODE_DESCRIPTION" : "LIVERPOOL",
      "POSTAL_ADDRESS_CODE" : "D",
      "POSTAL_ADDRESS_CODE_DESCRIPTION" : "A record which is linked to PAF",
      "BLPU_STATE_CODE" : null,
      "BLPU_STATE_CODE_DESCRIPTION" : "Unknown/Not applicable",
      "TOPOGRAPHY_LAYER_TOID" : "osgb1000002730053081",
      "PARENT_UPRN" : "38249360",
      "LAST_UPDATE_DATE" : "10/02/2016",
      "ENTRY_DATE" : "04/04/2008",
      "LANGUAGE" : "EN",
      "MATCH" : 1.0,
      "MATCH_DESCRIPTION" : "EXACT"
    }
  }, {
    "DPA" : {
      "UPRN" : "38250296",
      "UDPRN" : "28684592",
      "ADDRESS" : "APARTMENT 23, THE JAM WORKS 49-51, FLEET STREET, LIVERPOOL, L1 4AR",
      "SUB_BUILDING_NAME" : "APARTMENT 23",
      "BUILDING_NAME" : "THE JAM WORKS 49-51",
      "THOROUGHFARE_NAME" : "FLEET STREET",
      "POST_TOWN" : "LIVERPOOL",
      "POSTCODE" : "L1 4AR",
      "RPC" : "2",
      "X_COORDINATE" : 335018.0,
      "Y_COORDINATE" : 389970.0,
      "STATUS" : "APPROVED",
      "LOGICAL_STATUS_CODE" : "1",
      "CLASSIFICATION_CODE" : "RD06",
      "CLASSIFICATION_CODE_DESCRIPTION" : "Self Contained Flat (Includes Maisonette / Apartment)",
      "LOCAL_CUSTODIAN_CODE" : 4310,
      "LOCAL_CUSTODIAN_CODE_DESCRIPTION" : "LIVERPOOL",
      "POSTAL_ADDRESS_CODE" : "D",
      "POSTAL_ADDRESS_CODE_DESCRIPTION" : "A record which is linked to PAF",
      "BLPU_STATE_CODE" : null,
      "BLPU_STATE_CODE_DESCRIPTION" : "Unknown/Not applicable",
      "TOPOGRAPHY_LAYER_TOID" : "osgb1000002730053081",
      "PARENT_UPRN" : "38249360",
      "LAST_UPDATE_DATE" : "10/02/2016",
      "ENTRY_DATE" : "04/04/2008",
      "LANGUAGE" : "EN",
      "MATCH" : 1.0,
      "MATCH_DESCRIPTION" : "EXACT"
    }
  }, {
    "DPA" : {
      "UPRN" : "38250297",
      "UDPRN" : "28684593",
      "ADDRESS" : "APARTMENT 24, THE JAM WORKS 49-51, FLEET STREET, LIVERPOOL, L1 4AR",
      "SUB_BUILDING_NAME" : "APARTMENT 24",
      "BUILDING_NAME" : "THE JAM WORKS 49-51",
      "THOROUGHFARE_NAME" : "FLEET STREET",
      "POST_TOWN" : "LIVERPOOL",
      "POSTCODE" : "L1 4AR",
      "RPC" : "2",
      "X_COORDINATE" : 335018.0,
      "Y_COORDINATE" : 389970.0,
      "STATUS" : "APPROVED",
      "LOGICAL_STATUS_CODE" : "1",
      "CLASSIFICATION_CODE" : "RD06",
      "CLASSIFICATION_CODE_DESCRIPTION" : "Self Contained Flat (Includes Maisonette / Apartment)",
      "LOCAL_CUSTODIAN_CODE" : 4310,
      "LOCAL_CUSTODIAN_CODE_DESCRIPTION" : "LIVERPOOL",
      "POSTAL_ADDRESS_CODE" : "D",
      "POSTAL_ADDRESS_CODE_DESCRIPTION" : "A record which is linked to PAF",
      "BLPU_STATE_CODE" : null,
      "BLPU_STATE_CODE_DESCRIPTION" : "Unknown/Not applicable",
      "TOPOGRAPHY_LAYER_TOID" : "osgb1000002730053081",
      "PARENT_UPRN" : "38249360",
      "LAST_UPDATE_DATE" : "10/02/2016",
      "ENTRY_DATE" : "04/04/2008",
      "LANGUAGE" : "EN",
      "MATCH" : 1.0,
      "MATCH_DESCRIPTION" : "EXACT"
    }
  }, {
    "DPA" : {
      "UPRN" : "38250298",
      "UDPRN" : "28684594",
      "ADDRESS" : "APARTMENT 25, THE JAM WORKS 49-51, FLEET STREET, LIVERPOOL, L1 4AR",
      "SUB_BUILDING_NAME" : "APARTMENT 25",
      "BUILDING_NAME" : "THE JAM WORKS 49-51",
      "THOROUGHFARE_NAME" : "FLEET STREET",
      "POST_TOWN" : "LIVERPOOL",
      "POSTCODE" : "L1 4AR",
      "RPC" : "2",
      "X_COORDINATE" : 335018.0,
      "Y_COORDINATE" : 389970.0,
      "STATUS" : "APPROVED",
      "LOGICAL_STATUS_CODE" : "1",
      "CLASSIFICATION_CODE" : "RD06",
      "CLASSIFICATION_CODE_DESCRIPTION" : "Self Contained Flat (Includes Maisonette / Apartment)",
      "LOCAL_CUSTODIAN_CODE" : 4310,
      "LOCAL_CUSTODIAN_CODE_DESCRIPTION" : "LIVERPOOL",
      "POSTAL_ADDRESS_CODE" : "D",
      "POSTAL_ADDRESS_CODE_DESCRIPTION" : "A record which is linked to PAF",
      "BLPU_STATE_CODE" : null,
      "BLPU_STATE_CODE_DESCRIPTION" : "Unknown/Not applicable",
      "TOPOGRAPHY_LAYER_TOID" : "osgb1000002730053081",
      "PARENT_UPRN" : "38249360",
      "LAST_UPDATE_DATE" : "10/02/2016",
      "ENTRY_DATE" : "04/04/2008",
      "LANGUAGE" : "EN",
      "MATCH" : 1.0,
      "MATCH_DESCRIPTION" : "EXACT"
    }
  }, {
    "DPA" : {
      "UPRN" : "38250299",
      "UDPRN" : "28684595",
      "ADDRESS" : "APARTMENT 26, THE JAM WORKS 49-51, FLEET STREET, LIVERPOOL, L1 4AR",
      "SUB_BUILDING_NAME" : "APARTMENT 26",
      "BUILDING_NAME" : "THE JAM WORKS 49-51",
      "THOROUGHFARE_NAME" : "FLEET STREET",
      "POST_TOWN" : "LIVERPOOL",
      "POSTCODE" : "L1 4AR",
      "RPC" : "2",
      "X_COORDINATE" : 335018.0,
      "Y_COORDINATE" : 389970.0,
      "STATUS" : "APPROVED",
      "LOGICAL_STATUS_CODE" : "1",
      "CLASSIFICATION_CODE" : "RD06",
      "CLASSIFICATION_CODE_DESCRIPTION" : "Self Contained Flat (Includes Maisonette / Apartment)",
      "LOCAL_CUSTODIAN_CODE" : 4310,
      "LOCAL_CUSTODIAN_CODE_DESCRIPTION" : "LIVERPOOL",
      "POSTAL_ADDRESS_CODE" : "D",
      "POSTAL_ADDRESS_CODE_DESCRIPTION" : "A record which is linked to PAF",
      "BLPU_STATE_CODE" : null,
      "BLPU_STATE_CODE_DESCRIPTION" : "Unknown/Not applicable",
      "TOPOGRAPHY_LAYER_TOID" : "osgb1000002730053081",
      "PARENT_UPRN" : "38249360",
      "LAST_UPDATE_DATE" : "10/02/2016",
      "ENTRY_DATE" : "04/04/2008",
      "LANGUAGE" : "EN",
      "MATCH" : 1.0,
      "MATCH_DESCRIPTION" : "EXACT"
    }
  }, {
    "DPA" : {
      "UPRN" : "38250277",
      "UDPRN" : "28684572",
      "ADDRESS" : "APARTMENT 3, THE JAM WORKS 49-51, FLEET STREET, LIVERPOOL, L1 4AR",
      "SUB_BUILDING_NAME" : "APARTMENT 3",
      "BUILDING_NAME" : "THE JAM WORKS 49-51",
      "THOROUGHFARE_NAME" : "FLEET STREET",
      "POST_TOWN" : "LIVERPOOL",
      "POSTCODE" : "L1 4AR",
      "RPC" : "2",
      "X_COORDINATE" : 335018.0,
      "Y_COORDINATE" : 389970.0,
      "STATUS" : "APPROVED",
      "LOGICAL_STATUS_CODE" : "1",
      "CLASSIFICATION_CODE" : "RD06",
      "CLASSIFICATION_CODE_DESCRIPTION" : "Self Contained Flat (Includes Maisonette / Apartment)",
      "LOCAL_CUSTODIAN_CODE" : 4310,
      "LOCAL_CUSTODIAN_CODE_DESCRIPTION" : "LIVERPOOL",
      "POSTAL_ADDRESS_CODE" : "D",
      "POSTAL_ADDRESS_CODE_DESCRIPTION" : "A record which is linked to PAF",
      "BLPU_STATE_CODE" : null,
      "BLPU_STATE_CODE_DESCRIPTION" : "Unknown/Not applicable",
      "TOPOGRAPHY_LAYER_TOID" : "osgb1000002730053081",
      "PARENT_UPRN" : "38249360",
      "LAST_UPDATE_DATE" : "10/02/2016",
      "ENTRY_DATE" : "04/04/2008",
      "LANGUAGE" : "EN",
      "MATCH" : 1.0,
      "MATCH_DESCRIPTION" : "EXACT"
    }
  }, {
    "DPA" : {
      "UPRN" : "38250278",
      "UDPRN" : "28684573",
      "ADDRESS" : "APARTMENT 4, THE JAM WORKS 49-51, FLEET STREET, LIVERPOOL, L1 4AR",
      "SUB_BUILDING_NAME" : "APARTMENT 4",
      "BUILDING_NAME" : "THE JAM WORKS 49-51",
      "THOROUGHFARE_NAME" : "FLEET STREET",
      "POST_TOWN" : "LIVERPOOL",
      "POSTCODE" : "L1 4AR",
      "RPC" : "2",
      "X_COORDINATE" : 335018.0,
      "Y_COORDINATE" : 389970.0,
      "STATUS" : "APPROVED",
      "LOGICAL_STATUS_CODE" : "1",
      "CLASSIFICATION_CODE" : "RD06",
      "CLASSIFICATION_CODE_DESCRIPTION" : "Self Contained Flat (Includes Maisonette / Apartment)",
      "LOCAL_CUSTODIAN_CODE" : 4310,
      "LOCAL_CUSTODIAN_CODE_DESCRIPTION" : "LIVERPOOL",
      "POSTAL_ADDRESS_CODE" : "D",
      "POSTAL_ADDRESS_CODE_DESCRIPTION" : "A record which is linked to PAF",
      "BLPU_STATE_CODE" : null,
      "BLPU_STATE_CODE_DESCRIPTION" : "Unknown/Not applicable",
      "TOPOGRAPHY_LAYER_TOID" : "osgb1000002730053081",
      "PARENT_UPRN" : "38249360",
      "LAST_UPDATE_DATE" : "10/02/2016",
      "ENTRY_DATE" : "04/04/2008",
      "LANGUAGE" : "EN",
      "MATCH" : 1.0,
      "MATCH_DESCRIPTION" : "EXACT"
    }
  }, {
    "DPA" : {
      "UPRN" : "38250279",
      "UDPRN" : "28684574",
      "ADDRESS" : "APARTMENT 5, THE JAM WORKS 49-51, FLEET STREET, LIVERPOOL, L1 4AR",
      "SUB_BUILDING_NAME" : "APARTMENT 5",
      "BUILDING_NAME" : "THE JAM WORKS 49-51",
      "THOROUGHFARE_NAME" : "FLEET STREET",
      "POST_TOWN" : "LIVERPOOL",
      "POSTCODE" : "L1 4AR",
      "RPC" : "2",
      "X_COORDINATE" : 335018.0,
      "Y_COORDINATE" : 389970.0,
      "STATUS" : "APPROVED",
      "LOGICAL_STATUS_CODE" : "1",
      "CLASSIFICATION_CODE" : "RD06",
      "CLASSIFICATION_CODE_DESCRIPTION" : "Self Contained Flat (Includes Maisonette / Apartment)",
      "LOCAL_CUSTODIAN_CODE" : 4310,
      "LOCAL_CUSTODIAN_CODE_DESCRIPTION" : "LIVERPOOL",
      "POSTAL_ADDRESS_CODE" : "D",
      "POSTAL_ADDRESS_CODE_DESCRIPTION" : "A record which is linked to PAF",
      "BLPU_STATE_CODE" : null,
      "BLPU_STATE_CODE_DESCRIPTION" : "Unknown/Not applicable",
      "TOPOGRAPHY_LAYER_TOID" : "osgb1000002730053081",
      "PARENT_UPRN" : "38249360",
      "LAST_UPDATE_DATE" : "10/02/2016",
      "ENTRY_DATE" : "04/04/2008",
      "LANGUAGE" : "EN",
      "MATCH" : 1.0,
      "MATCH_DESCRIPTION" : "EXACT"
    }
  }, {
    "DPA" : {
      "UPRN" : "38250280",
      "UDPRN" : "28684575",
      "ADDRESS" : "APARTMENT 6, THE JAM WORKS 49-51, FLEET STREET, LIVERPOOL, L1 4AR",
      "SUB_BUILDING_NAME" : "APARTMENT 6",
      "BUILDING_NAME" : "THE JAM WORKS 49-51",
      "THOROUGHFARE_NAME" : "FLEET STREET",
      "POST_TOWN" : "LIVERPOOL",
      "POSTCODE" : "L1 4AR",
      "RPC" : "2",
      "X_COORDINATE" : 335018.0,
      "Y_COORDINATE" : 389970.0,
      "STATUS" : "APPROVED",
      "LOGICAL_STATUS_CODE" : "1",
      "CLASSIFICATION_CODE" : "RD06",
      "CLASSIFICATION_CODE_DESCRIPTION" : "Self Contained Flat (Includes Maisonette / Apartment)",
      "LOCAL_CUSTODIAN_CODE" : 4310,
      "LOCAL_CUSTODIAN_CODE_DESCRIPTION" : "LIVERPOOL",
      "POSTAL_ADDRESS_CODE" : "D",
      "POSTAL_ADDRESS_CODE_DESCRIPTION" : "A record which is linked to PAF",
      "BLPU_STATE_CODE" : null,
      "BLPU_STATE_CODE_DESCRIPTION" : "Unknown/Not applicable",
      "TOPOGRAPHY_LAYER_TOID" : "osgb1000002730053081",
      "PARENT_UPRN" : "38249360",
      "LAST_UPDATE_DATE" : "10/02/2016",
      "ENTRY_DATE" : "04/04/2008",
      "LANGUAGE" : "EN",
      "MATCH" : 1.0,
      "MATCH_DESCRIPTION" : "EXACT"
    }
  }, {
    "DPA" : {
      "UPRN" : "38250281",
      "UDPRN" : "28684576",
      "ADDRESS" : "APARTMENT 7, THE JAM WORKS 49-51, FLEET STREET, LIVERPOOL, L1 4AR",
      "SUB_BUILDING_NAME" : "APARTMENT 7",
      "BUILDING_NAME" : "THE JAM WORKS 49-51",
      "THOROUGHFARE_NAME" : "FLEET STREET",
      "POST_TOWN" : "LIVERPOOL",
      "POSTCODE" : "L1 4AR",
      "RPC" : "2",
      "X_COORDINATE" : 335018.0,
      "Y_COORDINATE" : 389970.0,
      "STATUS" : "APPROVED",
      "LOGICAL_STATUS_CODE" : "1",
      "CLASSIFICATION_CODE" : "RD06",
      "CLASSIFICATION_CODE_DESCRIPTION" : "Self Contained Flat (Includes Maisonette / Apartment)",
      "LOCAL_CUSTODIAN_CODE" : 4310,
      "LOCAL_CUSTODIAN_CODE_DESCRIPTION" : "LIVERPOOL",
      "POSTAL_ADDRESS_CODE" : "D",
      "POSTAL_ADDRESS_CODE_DESCRIPTION" : "A record which is linked to PAF",
      "BLPU_STATE_CODE" : null,
      "BLPU_STATE_CODE_DESCRIPTION" : "Unknown/Not applicable",
      "TOPOGRAPHY_LAYER_TOID" : "osgb1000002730053081",
      "PARENT_UPRN" : "38249360",
      "LAST_UPDATE_DATE" : "10/02/2016",
      "ENTRY_DATE" : "04/04/2008",
      "LANGUAGE" : "EN",
      "MATCH" : 1.0,
      "MATCH_DESCRIPTION" : "EXACT"
    }
  }, {
    "DPA" : {
      "UPRN" : "38250282",
      "UDPRN" : "28684577",
      "ADDRESS" : "APARTMENT 8, THE JAM WORKS 49-51, FLEET STREET, LIVERPOOL, L1 4AR",
      "SUB_BUILDING_NAME" : "APARTMENT 8",
      "BUILDING_NAME" : "THE JAM WORKS 49-51",
      "THOROUGHFARE_NAME" : "FLEET STREET",
      "POST_TOWN" : "LIVERPOOL",
      "POSTCODE" : "L1 4AR",
      "RPC" : "2",
      "X_COORDINATE" : 335018.0,
      "Y_COORDINATE" : 389970.0,
      "STATUS" : "APPROVED",
      "LOGICAL_STATUS_CODE" : "1",
      "CLASSIFICATION_CODE" : "RD06",
      "CLASSIFICATION_CODE_DESCRIPTION" : "Self Contained Flat (Includes Maisonette / Apartment)",
      "LOCAL_CUSTODIAN_CODE" : 4310,
      "LOCAL_CUSTODIAN_CODE_DESCRIPTION" : "LIVERPOOL",
      "POSTAL_ADDRESS_CODE" : "D",
      "POSTAL_ADDRESS_CODE_DESCRIPTION" : "A record which is linked to PAF",
      "BLPU_STATE_CODE" : null,
      "BLPU_STATE_CODE_DESCRIPTION" : "Unknown/Not applicable",
      "TOPOGRAPHY_LAYER_TOID" : "osgb1000002730053081",
      "PARENT_UPRN" : "38249360",
      "LAST_UPDATE_DATE" : "10/02/2016",
      "ENTRY_DATE" : "04/04/2008",
      "LANGUAGE" : "EN",
      "MATCH" : 1.0,
      "MATCH_DESCRIPTION" : "EXACT"
    }
  }, {
    "DPA" : {
      "UPRN" : "38250283",
      "UDPRN" : "28684578",
      "ADDRESS" : "APARTMENT 9, THE JAM WORKS 49-51, FLEET STREET, LIVERPOOL, L1 4AR",
      "SUB_BUILDING_NAME" : "APARTMENT 9",
      "BUILDING_NAME" : "THE JAM WORKS 49-51",
      "THOROUGHFARE_NAME" : "FLEET STREET",
      "POST_TOWN" : "LIVERPOOL",
      "POSTCODE" : "L1 4AR",
      "RPC" : "2",
      "X_COORDINATE" : 335018.0,
      "Y_COORDINATE" : 389970.0,
      "STATUS" : "APPROVED",
      "LOGICAL_STATUS_CODE" : "1",
      "CLASSIFICATION_CODE" : "RD06",
      "CLASSIFICATION_CODE_DESCRIPTION" : "Self Contained Flat (Includes Maisonette / Apartment)",
      "LOCAL_CUSTODIAN_CODE" : 4310,
      "LOCAL_CUSTODIAN_CODE_DESCRIPTION" : "LIVERPOOL",
      "POSTAL_ADDRESS_CODE" : "D",
      "POSTAL_ADDRESS_CODE_DESCRIPTION" : "A record which is linked to PAF",
      "BLPU_STATE_CODE" : null,
      "BLPU_STATE_CODE_DESCRIPTION" : "Unknown/Not applicable",
      "TOPOGRAPHY_LAYER_TOID" : "osgb1000002730053081",
      "PARENT_UPRN" : "38249360",
      "LAST_UPDATE_DATE" : "10/02/2016",
      "ENTRY_DATE" : "04/04/2008",
      "LANGUAGE" : "EN",
      "MATCH" : 1.0,
      "MATCH_DESCRIPTION" : "EXACT"
    }
  } ]
}
